Workbook

Sheet Instructions
A3: Sheets in this workbook:
A4: • Orders_Extract - 4,000-row sample of orders joined with customer info (deliberately messy)
A5: • OrderLines_Extract - 4,000-row sample of order line items joined with product & order info
A7: Your tasks (see the full Student Brief for details):
A8: 1. On a COPY of each sheet, clean obvious data-quality issues you find (inconsistent state names/casing,
A9: stray whitespace, mixed-case status/tier text, negative shipping costs, etc.). Use formulas
A10: (TRIM, PROPER, UPPER, IF, IFERROR) - do not just retype values by hand.
A11: 2. Build at least TWO PivotTables: e.g. (a) total revenue by state and membership_tier,
A12: (b) total quantity and revenue by product category and channel.
A13: 3. Build at least ONE PivotChart from one of your PivotTables.
A14: 4. Add a 'Descriptive_Stats' sheet with AVERAGE, MEDIAN, STDEV, MIN, MAX and COUNT for total_amount
A15: and shipping_cost, computed with formulas (not typed-in numbers).
... A20: analysis in later phases must use the FULL CSV files in data/raw/, not this workbook.

Sheet Orders_Extract
B1: customer_id | C1: order_date | D1: channel | E1: order_status | F1: payment_method | G1: shipping_cost | H1: discount_pct | I1: total_amount | J1: first_name | K1: last_name | L1: state | M1: membership_tier | N1: signup_date
A2: ORD127194 | B2: CUST001908 | C2: 2025-05-31 | D2: In-Store | E2: Completed | F2: PayPal | G2: 5.99 | H2: 0 | I2: 607.63 | J2: Ashley | K2: Hester | L2: Indiana | M2: BRONZE | N2: 05/18/2025
A3: ORD109227 | B3: CUST004626 | C3: 2025-08-22 | D3: Mobile App | E3: Returned | F3: Gift Card | G3: 0 | H3: 15 | I3: 1195.8 | J3: Leah | K3: Whitaker | L3: WISCONSIN | M3: gold | N3: 2024-03-22
A4: ORD109077 | B4: CUST000733 | C4: 2024-09-16 | D4: Online | E4: Cancelled | F4: Debit Card | G4: 4.99 | H4: 0 | I4: 2670.39 | J4: Bryan | K4: Holt | L4: GA | M4: Gold | N4: 2022-12-27
A5: ORD100396 | B5: CUST002155 | C5: 2025-04-14 | D5: Mobile App | E5: Pending | F5: Credit Card | G5: 0 | H5: 0 | I5: 2207.73 | J5: Dennis | K5: Rowe | L5: PA | M5: Bronze | N5: 2025-04-02
A6: ORD113973 | B6: CUST001459 | C6: 2023-10-12 | D6: Online | E6: Completed | F6: PayPal | G6: 0 | H6: 0 | I6: 755.59 | J6: Brett | K6: Ashley | L6: NY | M6: silver | N6: 2022-12-15
A7: ORD126188 | B7: CUST005599 | C7: 2023-07-19 | D7: Mobile App | E7: Pending | F7: Gift Card | G7: 4.99 | H7: 0 | I7: 608.18 | J7: Molly | K7: Serrano | L7: Wisconsin | M7: gold | N7: 2021-01-04
A8: ORD119947 | B8: CUST005844 | C8: 2026-05-04 | D8: Mobile App | E8: Completed | F8: Debit Card | G8: 0 | H8: 0 | I8: 2447.22 | J8: William | K8: Luna | L8: OH | M8: BRONZE | N8: 2024-08-31
A9: ORD116133 | B9: CUST001071 | C9: 2022-02-02 | D9: Online | E9: Completed | F9: Gift Card | G9: 0 | H9: 5 | I9: 1552.8 | J9: James | K9: Mullen | L9: Michigan | M9: Silver | N9: 2020-09-24
A10: ORD125114 | B10: CUST005141 | C10: 2026-03-10 | D10: Online | E10: Completed | F10: PayPal | G10: 12.99 | H10: 5 | I10: 458.04 | J10: Jose | K10: Owens | L10: New York | M10: Platinum | N10: 2026-03-05
A11: ORD103892 | B11: CUST004318 | C11: 2025-02-22 | D11: Online | E11: Completed | F11: Debit Card | G11: 12.99 | H11: 0 | I11: 130.99 | J11: Monica | K11: Williams | L11: NC | M11: BRONZE | N11: 2024-12-21
A12: ORD118451 | B12: CUST004089 | C12: 2024-10-02 | D12: Online | E12: Completed | F12: Store Credit | G12: 0 | H12: 10 | I12: 1380.19 | J12: Laura | K12: Parrish | L12: Missouri | M12: Platinum | N12: 2022-08-31
A13: ORD107271 | B13: CUST004048 | C13: 2024-01-09 | D13: Mobile App | E13: Completed | F13: Store Credit | G13: 7.99 | H13: 0 | I13: 944.14 | J13: Eric | K13: Mosley | L13: tx | M13: BRONZE | N13: 2020-10-21
... A75: ORD124934 | B75: CUST005527 | C75: 2024-07-17 | D75: Mobile App | E75: Completed | F75: Debit Card | G75: 4.99 | H75: 0 | I75: 392.77 | J75: Terrance | K75: Donovan | L75: va | M75: gold | N75: 2024-06-21
A76: ORD101585 | B76: CUST006044 | D76: In-Store | E76: Completed | F76: PayPal | G76: 4.99 | H76: 0 | I76: 932.21 | J76: Jonathan | K76: Collins | L76: Pennsylvania | M76: platinum | N76: 2021-11-11
A77: ORD101196 | B77: CUST002069 | C77: 2025-05-11 | D77: Online | E77: Completed | F77: Credit Card | G77: 7.99 | H77: 15 | I77: 2816.23 | J77: Crystal | K77: Wilkinson | L77: ga | M77: BRONZE | N77: 2020-09-24
A78: ORD119297 | B78: CUST000059 | C78: 2023-05-08 | D78: In-Store | E78: Completed | F78: Gift Card | G78: 0 | H78: 0 | I78: 470.35 | J78: Joseph | K78: Martinez | L78: NC | M78: bronze | N78: 2021-05-02
A79: ORD112147 | B79: CUST000033 | C79: 2025-04-02 | D79: Mobile App | E79: Completed | F79: Credit Card | G79: 0 | H79: 0 | I79: 994.12 | J79: Ashley | K79: Barnett | L79: PA | M79: silver | N79: 2023-07-20
A80: ORD126366 | B80: CUST004904 | C80: 2024-06-04 | D80: Online | E80: Returned | F80: Debit Card | G80: 4.99 | H80: 0 | I80: 1079.59 | J80: Robert | K80: Allen | L80: VA | M80: SILVER | N80: 2022-07-14
A81: ORD124737 | B81: CUST000122 | C81: 2023-10-30 | D81: In-Store | E81: Completed | F81: Gift Card | G81: 4.99 | H81: 0 | I81: 1876.46 | J81: Christopher | K81: Bruce | L81: IL | M81: Bronze | N81: 2022-08-08
A82: ORD125909 | B82: CUST003077 | C82: 2025-12-29 | D82: Mobile App | E82: Completed | F82: Gift Card | G82: 7.99 | H82: 0 | I82: 1131.9 | J82: Jesse | K82: Drake | L82: md | M82: BRONZE | N82: 2025-01-02
A83: ORD114677 | B83: CUST005677 | C83: 2026-02-09 | D83: Online | E83: Completed | F83: Debit Card | G83: 5.99 | H83: 0 | I83: 2524.15 | J83: Tara | K83: Jenkins | L83: OH | M83: Bronze | N83: 2023-07-20
A84: ORD110512 | B84: CUST006072 | C84: 2025-07-26 | D84: In-Store | E84: Completed | F84: Store Credit | G84: 0 | H84: 0 | I84: 3822.57 | J84: Tracy | K84: Haley | L84: ARIZONA | M84: bronze | N84: 2025-07-26
A85: ORD117570 | B85: CUST004321 | C85: 2023-02-01 | D85: In-Store | E85: Completed | F85: Gift Card | G85: 7.99 | H85: 0 | I85: 984.33 | J85: Timothy | K85: Garcia | L85: NY | M85: bronze | N85: 2020-09-11
A86: ORD106915 | B86: CUST001841 | C86: 2024-05-20 | D86: In-Store | E86: Cancelled | F86: Credit Card | G86: 0 | H86: 0 | I86: 2786.87 | J86: Peter | K86: Phillips | L86: OH | M86: Bronze | N86: 2024-02-07
A87: ORD120520 | B87: CUST003431 | C87: 2024-10-01 | D87: Mobile App | E87: Completed | F87: PayPal | G87: 7.99 | H87: 5 | I87: 740.23 | J87: Yvonne | K87: Short | L87: AZ | M87: Bronze | N87: 2024-08-16
A88: ORD113169 | B88: CUST001610 | D88: Mobile App | E88: Completed | F88: Store Credit | G88: 12.99 | H88: 0 | I88: 2780.86 | J88: Manuel | K88: Brandt | L88: NY | M88: silver | N88: 2024-09-22
A89: ORD101552 | B89: CUST005452 | C89: 2024-08-01 | D89: In-Store | E89: Returned | F89: PayPal | G89: 12.99 | H89: 5 | I89: 6972.53 | J89: Emily | K89: Freeman | L89: mo | M89: bronze | N89: 2023-02-19
A90: ORD122358 | B90: CUST000020 | C90: 2025-06-10 | D90: In-Store | E90: Completed | F90: PayPal | G90: 5.99 | H90: 5 | I90: 928.98 | J90: Monica | K90: Garrison | L90: GA | M90: Silver | N90: 2025-06-05
A91: ORD117828 | B91: CUST003076 | C91: 2025-12-17 | D91: Online | E91: Completed | F91: Gift Card | G91: 0 | H91: 0 | I91: 1644.43 | J91: Benjamin | K91: Phillips | L91: IN | M91: BRONZE | N91: 2022-03-11
A92: ORD109281 | B92: CUST001154 | C92: 2025-03-14 | D92: In-Store | E92: Completed | F92: Store Credit | G92: 7.99 | H92: 0 | I92: 2228.29 | J92: Tracy | K92: Hoffman | L92: Arizona | M92: Gold | N92: 2022-07-21
A93: ORD111335 | B93: CUST004155 | C93: 2022-09-05 | D93: Mobile App | E93: Completed | F93: PayPal | G93: 7.99 | H93: 0 | I93: 3197.45 | J93: Emily | K93: Clark | L93: Missouri | M93: Silver | N93: 2020-11-06
A94: ORD125307 | B94: CUST003733 | C94: 2024-09-25 | D94: In-Store | E94: Completed | F94: Store Credit | G94: 0 | H94: 0 | I94: 2618.68 | J94: Randall | K94: Robinson | L94: MA | M94: GOLD | N94: 2021-07-24
A95: ORD117581 | B95: CUST004860 | C95: 2026-02-25 | D95: Mobile App | E95: Completed | F95: Debit Card | G95: 0 | H95: 15 | I95: 1959.91 | J95: Charles | K95: Vaughn | L95: Illinois | M95: bronze | N95: 2025-10-25
A96: ORD110821 | B96: CUST001728 | C96: 2024-11-03 | D96: Mobile App | E96: Completed | F96: Debit Card | G96: 7.99 | H96: 0 | I96: 2221.49 | J96: Katherine | K96: Turner | L96: NJ | M96: Silver | N96: 2024-01-20
A97: ORD126157 | B97: CUST001402 | C97: 2024-05-29 | D97: In-Store | E97: Completed | F97: Gift Card | G97: 12.99 | H97: 0 | I97: 282.76 | J97: Krista | K97: Castillo | L97: wa | M97: BRONZE | N97: 2022-10-02
A98: ORD112720 | B98: CUST002930 | C98: 2025-10-12 | D98: Online | E98: Completed | F98: Credit Card | G98: 0 | H98: 0 | I98: 2488.5 | J98: Cindy | K98: Harris | L98: NY | M98: SILVER | N98: 2025-06-11
A99: ORD119550 | B99: CUST004613 | C99: 2025-06-01 | D99: Mobile App | E99: Completed | F99: Debit Card | G99: 5.99 | H99: 0 | I99: 2064.19 | J99: Kristen | K99: Hoover | L99: NORTH CAROLINA | M99: bronze | N99: 10/30/2022
A100: ORD104485 | B100: CUST005794 | C100: 2022-05-20 | D100: Mobile App | E100: Completed | F100: Credit Card | G100: 4.99 | H100: 0 | I100: 4674.21 | J100: Haley | K100: King | L100: Pennsylvania | M100: bronze | N100: 2021-05-27
... A230: ORD103402 | B230: CUST005373 | C230: 2026-06-10 | D230: Mobile App | E230: Completed | F230: PayPal | G230: 4.99 | H230: 20 | I230: 787.84 | J230: Kayla | K230: Spence | L230: NEW JERSEY | M230: Bronze | N230: 2023-08-03
A231: ORD117682 | B231: CUST002251 | D231: Mobile App | E231: Completed | F231: Debit Card | G231: 5.99 | H231: 0 | I231: 19.64 | J231: Courtney | K231: Parks | L231: Maryland | M231: gold | N231: 2022-06-02
A232: ORD122212 | B232: CUST003953 | C232: 2023-12-16 | D232: Mobile App | E232: COMPLETED | F232: Credit Card | G232: 4.99 | H232: 0 | I232: 1841.18 | J232: Richard | K232: Watkins | L232: NC | M232: Bronze | N232: 2023-06-27
A233: ORD112414 | B233: CUST002913 | C233: 2025-05-12 | D233: In-Store | E233: Completed | F233: Gift Card | G233: 5.99 | H233: 5 | I233: 2837.6 | J233: Eric | K233: Colon | L233: Wisconsin | M233: SILVER | N233: 2025-04-27
A234: ORD113551 | B234: CUST004566 | C234: 2026-04-16 | D234: Mobile App | E234: COMPLETED | F234: Debit Card | G234: 5.99 | H234: 0 | I234: 1191.98 | J234: Cindy | K234: Johnston | L234: NJ | M234: GOLD | N234: 2026-04-12
A235: ORD102803 | B235: CUST002466 | C235: 2025-04-13 | D235: Mobile App | E235: completed | F235: Store Credit | G235: 12.99 | H235: 15 | I235: 3640.92 | J235: Sean | K235: Krueger | L235: VA | M235: Bronze | N235: 2025-04-12
A236: ORD117007 | B236: CUST001627 | C236: 2026-06-23 | D236: In-Store | E236: Returned | F236: Credit Card | G236: 0 | H236: 0 | I236: 1403.95 | J236: Daniel | K236: Rasmussen | L236: AZ | M236: BRONZE | N236: 2026-06-21
A237: ORD117970 | B237: CUST002237 | C237: 2025-02-14 | D237: In-Store | E237: Completed | F237: Credit Card | G237: 7.99 | H237: 0 | I237: 776.92 | J237: Joshua | K237: Gregory | L237: FLORIDA | M237: Bronze | N237: 2024-06-10
A238: ORD104814 | B238: CUST004249 | C238: 2026-04-12 | D238: In-Store | E238: Completed | F238: Credit Card | G238: 0 | H238: 5 | I238: 1267.93 | J238: James | K238: Daniel | L238: Massachusetts | M238: Bronze | N238: 2026-04-09
A239: ORD116784 | B239: CUST004801 | C239: 2026-06-18 | D239: In-Store | E239: Completed | F239: Gift Card | G239: 0 | H239: 0 | I239: 1605.29 | J239: Joanne | K239: Lloyd | L239: PENNSYLVANIA | M239: Gold | N239: 09/06/2022
A240: ORD123098 | B240: CUST004080 | C240: 2024-03-13 | D240: Online | E240: Cancelled | F240: Credit Card | G240: 5.99 | H240: 0 | I240: 367.73 | J240: Jimmy | K240: Martin | L240: Washington | M240: Bronze | N240: 2024-02-11
A241: ORD118886 | B241: CUST001551 | C241: 2026-02-15 | D241: In-Store | E241: Completed | F241: Credit Card | G241: 12.99 | H241: 10 | I241: 756.2 | J241: Nicole | K241: Thomas | L241: Tennessee | M241: bronze | N241: 2024-05-31
A242: ORD113639 | B242: CUST000513 | C242: 2025-05-09 | D242: Mobile App | E242: Completed | F242: Gift Card | G242: 5.99 | H242: 0 | I242: 974.93 | J242: Victor | K242: Stewart | L242: AZ | M242: Gold | N242: 2024-08-05
A243: ORD126020 | B243: CUST002600 | C243: 2022-10-24 | D243: Online | E243: Completed | F243: Credit Card | G243: 7.99 | H243: 0 | I243: 3074.39 | J243: Rhonda | K243: Olson | L243: IN | M243: Bronze | N243: 2022-06-11
... A296: ORD115317 | B296: CUST000919 | C296: 2023-05-01 | D296: Online | E296: Completed | F296: Store Credit | G296: 4.99 | H296: 0 | I296: 2586.23 | J296: Brandon | K296: Lowe | L296: MO | M296: Bronze | N296: 2022-06-14
A297: ORD107724 | B297: CUST002874 | D297: Online | E297: Cancelled | F297: Gift Card | G297: 7.99 | H297: 0 | I297: 1681.07 | J297: Howard | K297: Monroe | L297: Michigan | M297: Platinum | N297: 11/29/2022
A298: ORD127160 | B298: CUST005311 | C298: 2025-09-27 | D298: Online | E298: Completed | F298: Gift Card | G298: 12.99 | H298: 0 | I298: 2432.51 | J298: Misty | K298: Miller | L298: NEW JERSEY | M298: BRONZE | N298: 2024-12-26
A299: ORD125221 | B299: CUST003528 | C299: 2026-04-11 | D299: Mobile App | E299: Completed | F299: Credit Card | G299: 0 | H299: 0 | I299: 576.36 | J299: George | K299: Hunter | L299: Michigan | M299: Platinum | N299: 2025-07-29
A300: ORD109692 | B300: CUST002286 | C300: 2025-03-13 | D300: Mobile App | E300: Completed | F300: Store Credit | G300: 0 | H300: 0 | I300: 81.7 | J300: Heather | K300: Johnson | L300: California | M300: BRONZE | N300: 2023-11-05
A301: ORD115805 | B301: CUST002730 | C301: 2025-11-19 | D301: Online | E301: Completed | F301: Credit Card | G301: 4.99 | H301: 0 | I301: 1679.55 | J301: Yolanda | K301: Bolton | L301: CA | M301: gold | N301: 2025-11-18
A302: ORD124069 | B302: CUST002159 | C302: 2025-10-07 | D302: Online | E302: Completed | F302: Credit Card | G302: 12.99 | H302: 0 | I302: 1167.98 | J302: Jason | K302: James | L302: Pennsylvania | M302: Bronze | N302: 09/14/2024
A303: ORD125396 | B303: CUST001360 | C303: 2025-06-04 | D303: Mobile App | E303: COMPLETED | F303: Gift Card | G303: 5.99 | H303: 0 | I303: 2371.38 | J303: James | K303: Mathis | L303: Washington | M303: gold | N303: 2025-01-09
A304: ORD101444 | B304: CUST004765 | C304: 2026-05-07 | D304: Online | E304: Completed | F304: Store Credit | G304: 0 | H304: 0 | I304: 1764.14 | J304: Cheyenne | K304: Hanson | L304: Illinois | M304: Bronze | N304: 2025-11-07
A305: ORD117420 | B305: CUST004399 | C305: 2025-06-05 | D305: In-Store | E305: Completed | F305: PayPal | G305: 0 | H305: 10 | I305: 3685.64 | J305: Melissa | K305: Martin | L305: New Jersey | M305: Gold | N305: 05/22/2023
A306: ORD104732 | B306: CUST002323 | C306: 2025-10-22 | D306: Online | E306: Completed | F306: PayPal | G306: 4.99 | H306: 0 | I306: 1233.11 | J306: Kathleen | K306: Weaver | L306: Massachusetts | M306: bronze | N306: 2023-01-25
A307: ORD127662 | B307: CUST003249 | C307: 2026-02-07 | D307: In-Store | E307: Completed | F307: PayPal | G307: 12.99 | H307: 0 | I307: 2124.01 | J307: Bobby | K307: Rojas | L307: Tennessee | M307: silver | N307: 2025-09-17
A308: ORD111135 | B308: CUST001210 | C308: 2025-07-23 | D308: In-Store | E308: Completed | F308: Credit Card | G308: 0 | H308: 10 | I308: 3868.04 | J308: Vickie | K308: Jackson | L308: il | M308: bronze | N308: 2022-04-09
A309: ORD111586 | B309: CUST002429 | C309: 2024-07-11 | D309: In-Store | E309: Completed | F309: PayPal | G309: 0 | H309: 0 | I309: 1762.86 | J309: Joel | K309: Monroe | L309: in | M309: SILVER | N309: 2023-04-01
... A356: ORD112866 | B356: CUST000271 | C356: 2023-09-29 | D356: Online | E356: Completed | F356: Credit Card | G356: 0 | H356: 0 | I356: 1336.44 | J356: Catherine | K356: Salazar | L356: WI | M356: Bronze | N356: 2022-01-06
A357: ORD121018 | B357: CUST005474 | D357: In-Store | E357: Completed | F357: Debit Card | G357: 7.99 | H357: 0 | I357: 488.43 | J357: Caitlyn | K357: Salas | L357: New Jersey | M357: BRONZE | N357: 2021-12-06
A358: ORD114049 | B358: CUST001952 | C358: 2025-05-16 | D358: Online | E358: Completed | F358: Debit Card | G358: 4.99 | H358: 0 | I358: 1332.95 | J358: Jessica | K358: Perez | L358: NY | M358: bronze | N358: 2022-02-09
A359: ORD117160 | B359: CUST001503 | C359: 2026-06-12 | D359: Mobile App | E359: Completed | F359: Gift Card | G359: 0 | H359: 0 | I359: 2110.72 | J359: Heather | K359: Reeves | L359: IN | M359: Silver | N359: 2026-06-12
A360: ORD127374 | B360: CUST003489 | C360: 2026-06-08 | D360: Mobile App | E360: COMPLETED | F360: PayPal | G360: 4.99 | H360: 0 | I360: 2380.87 | J360: James | K360: Nguyen | L360: North Carolina | M360: BRONZE | N360: 2024-06-05
A361: ORD109156 | B361: CUST005131 | C361: 2023-10-16 | D361: Online | E361: Completed | F361: Debit Card | G361: 0 | H361: 0 | I361: 271.98 | J361: Anthony | K361: Mosley | L361: VA | M361: SILVER | N361: 2021-04-24
A362: ORD100277 | B362: CUST006049 | C362: 2024-09-21 | D362: Mobile App | E362: Completed | F362: Store Credit | G362: 0 | H362: 0 | I362: 341.46 | J362: Joel | K362: Snyder | L362: PA | M362: Gold | N362: 2024-01-02
A363: ORD124071 | B363: CUST002159 | C363: 2026-03-21 | D363: Mobile App | E363: Completed | F363: Debit Card | G363: 7.99 | H363: 5 | I363: 3175.65 | J363: Jason | K363: James | L363: Pennsylvania | M363: Bronze | N363: 09/14/2024
A364: ORD120412 | B364: CUST000987 | C364: 2024-11-27 | D364: Online | E364: Completed | F364: Gift Card | G364: 7.99 | H364: 10 | I364: 3003.35 | J364: Ashley | K364: Cortez | L364: California | M364: Silver | N364: 2022-12-02
A365: ORD104241 | B365: CUST003266 | C365: 2024-11-17 | D365: Online | E365: Completed | F365: Gift Card | G365: 12.99 | H365: 0 | I365: 850.54 | J365: Jeremy | K365: Hubbard | L365: Massachusetts | M365: gold | N365: 2023-11-19
A366: ORD127503 | B366: CUST004419 | C366: 2022-10-29 | D366: Online | E366: Completed | F366: PayPal | G366: 0 | H366: 0 | I366: 2961.73 | J366: Ashley | K366: Thompson | L366: FLORIDA | M366: Bronze | N366: 2022-07-03
A367: ORD111032 | B367: CUST004950 | C367: 2022-07-05 | D367: Mobile App | E367: Completed | F367: Store Credit | G367: 12.99 | H367: 0 | I367: 364.87 | J367: Denise | K367: Williams | L367: OH | M367: bronze | N367: 2021-06-24
A368: ORD116155 | B368: CUST004934 | C368: 2022-04-09 | D368: Mobile App | E368: Completed | F368: Gift Card | G368: 5.99 | H368: 0 | I368: 43.51 | J368: Erika | K368: Lopez | L368: Pennsylvania | M368: Silver | N368: 2021-05-29
A369: ORD102921 | B369: CUST003559 | C369: 2024-04-02 | D369: Mobile App | E369: Completed | F369: PayPal | G369: 12.99 | H369: 0 | I369: 127.94 | J369: Lindsay | K369: Jones | L369: WA | M369: Bronze | N369: 2022-01-11
... A416: ORD120840 | B416: CUST005560 | C416: 2026-05-26 | D416: Mobile App | E416: Completed | F416: Store Credit | G416: 4.99 | H416: 0 | I416: 3077.76 | J416: Troy | K416: Bates | L416: NY | M416: Gold | N416: 2026-05-16
A417: ORD109390 | B417: CUST004955 | D417: Mobile App | E417: Completed | F417: Store Credit | G417: 7.99 | H417: 0 | I417: 1596.69 | J417: Patricia | K417: Thompson | L417: NY | M417: BRONZE | N417: 2024-02-18
A418: ORD103953 | B418: CUST002804 | C418: 2025-01-25 | D418: Online | E418: Completed | F418: Store Credit | G418: 12.99 | H418: 0 | I418: 498.76 | J418: Brenda | K418: Jennings | L418: New Jersey | M418: SILVER | N418: 2024-02-06
A419: ORD124484 | B419: CUST001685 | C419: 2025-03-15 | D419: Online | E419: Completed | F419: Store Credit | G419: 12.99 | H419: 0 | I419: 2840.21 | J419: Megan | K419: Mcdonald | L419: Indiana | M419: Bronze | N419: 2025-01-14
A420: ORD127121 | B420: CUST003060 | C420: 2026-04-05 | D420: Mobile App | E420: Completed | F420: Debit Card | G420: 5.99 | H420: 15 | I420: 1564.46 | J420: Christopher | K420: Meza | L420: TX | M420: Silver | N420: 2024-01-21
A421: ORD125817 | B421: CUST000411 | C421: 2025-04-09 | D421: Mobile App | E421: Pending | F421: Store Credit | G421: 5.99 | H421: 15 | I421: 593.03 | J421: Sherry | K421: Parsons | L421: fl | M421: GOLD | N421: 2025-02-13
A422: ORD124400 | B422: CUST002971 | C422: 2024-10-02 | D422: Online | E422: Completed | F422: Store Credit | G422: 7.99 | H422: 10 | I422: 442.64 | J422: Jeremy | K422: Davis | L422: NJ | M422: Bronze | N422: 2024-06-17
A423: ORD125851 | B423: CUST000193 | C423: 2023-07-07 | D423: Mobile App | E423: Completed | F423: Credit Card | G423: 4.99 | H423: 15 | I423: 1421.33 | J423: Joanna | K423: Davis | L423: TEXAS | M423: silver | N423: 2020-12-09
A424: ORD125040 | B424: CUST000222 | C424: 2021-07-19 | D424: In-Store | E424: Completed | F424: Gift Card | G424: 0 | H424: 0 | I424: 823.42 | J424: Crystal | K424: Williams | L424: CA | M424: Silver | N424: 2020-12-30
A425: ORD127369 | B425: CUST004656 | C425: 2024-11-14 | D425: Online | E425: Completed | F425: Store Credit | G425: 7.99 | H425: 10 | I425: 417.92 | J425: Jennifer | K425: Burnett | L425: VIRGINIA | M425: silver | N425: 2022-07-12
A426: ORD118588 | B426: CUST002633 | C426: 2025-09-07 | D426: Online | E426: Completed | F426: Debit Card | G426: 7.99 | H426: 0 | I426: 809.59 | J426: Joanna | K426: Dunlap | L426: MA | M426: Platinum | N426: 2025-09-06
A427: ORD122964 | B427: CUST001738 | C427: 2026-04-24 | D427: Mobile App | E427: Completed | F427: Gift Card | G427: 0 | H427: 0 | I427: 844.37 | J427: Danielle | K427: Shepard | L427: PA | M427: bronze | N427: 2026-04-23
A428: ORD100665 | B428: CUST004564 | C428: 2022-05-04 | D428: In-Store | E428: Completed | F428: PayPal | G428: 12.99 | H428: 0 | I428: 2566.83 | J428: Michelle | K428: Hicks | L428: OH | M428: SILVER | N428: 2021-06-09
A429: ORD119070 | B429: CUST003114 | C429: 2022-10-24 | D429: In-Store | E429: Completed | F429: Store Credit | G429: 12.99 | H429: 0 | I429: 131.16 | J429: Devon | K429: Vaughan | L429: Tennessee | M429: silver | N429: 2021-02-02
... A433: ORD127431 | B433: CUST003842 | C433: 2022-08-24 | D433: Online | E433: Completed | F433: Store Credit | G433: 0 | H433: 0 | I433: 1180.69 | J433: Johnathan | K433: Hoffman | L433: FL | M433: bronze | N433: 2021-06-14
A434: ORD101919 | B434: CUST003882 | D434: In-Store | E434: Completed | F434: Store Credit | G434: 4.99 | H434: 0 | I434: 738.32 | J434: Kevin | K434: Smith | L434: WI | M434: bronze | N434: 2025-10-31
A435: ORD104571 | B435: CUST003603 | C435: 2024-07-29 | D435: Online | E435: Completed | F435: Store Credit | G435: 0 | H435: 0 | I435: 5239.38 | J435: Heather | K435: Torres | L435: nc | M435: SILVER | N435: 2022-10-15
A436: ORD121444 | B436: CUST005249 | C436: 2026-04-12 | D436: Mobile App | E436: Completed | F436: Credit Card | G436: 7.99 | H436: 5 | I436: 982.97 | J436: Alexis | K436: Morris | L436: IL | M436: Bronze | N436: 2026-04-08
A437: ORD119499 | B437: CUST002184 | C437: 2025-05-21 | D437: Mobile App | E437: Completed | F437: Store Credit | G437: 4.99 | H437: 20 | I437: 966.55 | J437: Nathan | K437: Fisher | L437: ny | M437: Gold | N437: 2022-10-25
...

Sheet OrderLines_Extract
A1: order_item_id | B1: order_id | C1: product_id | D1: quantity | E1: unit_price_at_purchase | F1: product_name | G1: category | H1: sub_category | I1: brand | J1: customer_id | K1: order_date | L1: channel | M1: order_status
A2: OI502661 | B2: ORD124764 | C2: PROD1007 | D2: 1 | E2: 119.59 | F2: Meridian Basics Wellness X | G2: Beauty & Personal Care | H2: Wellness | I2: Meridian Basics | J2: CUST002442 | K2: 2024-01-03 | L2: Online | M2: Completed
A3: OI504251 | B3: ORD123647 | C3: PROD1066 | D3: 1 | E3: 92.95 | F3: Northfield Fragrance Max | G3: Beauty & Personal Care | H3: Fragrance | I3: Northfield | J3: CUST003540 | K3: 2025-04-09 | L3: Mobile App | M3: Completed
A4: OI563095 | B4: ORD120357 | C4: PROD1033 | D4: 3 | E4: 147.37 | F4: Crestline Wellness Classic | G4: Beauty & Personal Care | H4: Wellness | I4: Crestline | J4: CUST003336 | K4: 2026-01-09 | L4: Online | M4: Completed
A5: OI508966 | B5: ORD109049 | C5: PROD1211 | D5: 1 | E5: 79.19 | F5: Amberly Bedding | G5: Home & Kitchen | H5: Bedding | I5: Amberly | J5: CUST004023 | K5: 2026-04-04 | L5: In-Store | M5: Completed
A6: OI533946 | B6: ORD127684 | C6: PROD1152 | D6: 3 | E6: 792.04 | F6: Vertex Smartphone Lite | G6: Electronics | H6: Smartphones | I6: Vertex | J6: CUST001077 | K6: 2025-03-21 | L6: Online | M6: Completed
A7: OI540748 | B7: ORD121329 | C7: PROD1163 | D7: 1 | E7: 471.74 | F7: Pinecrest Small Appliances Essential | G7: Home & Kitchen | H7: Small Appliances | I7: Pinecrest | J7: CUST000441 | K7: 2025-12-06 | L7: Mobile App | M7: Completed
A8: OI524525 | B8: ORD104018 | C8: PROD1122 | D8: 3 | E8: 26.31 | F8: Solstice Headphones Essential | G8: Electronics | H8: Headphones | I8: Solstice | J8: CUST001843 | K8: 2024-06-27 | L8: Mobile App | M8: Cancelled
A9: OI504130 | B9: ORD118883 | C9: PROD1158 | D9: 2 | E9: 248.11 | F9: Pinecrest Accessories Plus | G9: Apparel | H9: Accessories | I9: Pinecrest | J9: CUST004873 | K9: 2024-02-15 | L9: Online | M9: Returned
A10: OI568470 | B10: ORD123588 | C10: PROD1106 | D10: 1 | E10: 419.77 | F10: Orion Team Sport Pro | G10: Sports & Outdoors | H10: Team Sports | I10: Orion | J10: CUST003497 | K10: 2023-11-29 | L10: In-Store | M10: Completed
A11: OI571275 | B11: ORD101564 | C11: PROD1071 | D11: 1 | E11: 342.46 | F11: Crestline Cycling Plus | G11: Sports & Outdoors | H11: Cycling | I11: Crestline | J11: CUST002458 | K11: 2025-10-26 | L11: Online | M11: Completed
A12: OI511685 | B12: ORD100958 | C12: PROD1050 | D12: 1 | E12: 36.47 | F12: TrueForm Bedding Essential | G12: Home & Kitchen | H12: Bedding | I12: TrueForm | J12: CUST001439 | K12: 2021-09-12 | L12: Online | M12: Completed
A13: OI520686 | B13: ORD121250 | C13: PROD1011 | D13: 2 | E13: 215.43 | F13: Solstice Small Appliances Lite | G13: Home & Kitchen | H13: Small Appliances | I13: Solstice | J13: CUST002939 | K13: 2025-08-06 | L13: Mobile App | M13: Completed
... A39: OI519957 | B39: ORD113745 | C39: PROD1132 | D39: 1 | E39: 806.53 | F39: Pinecrest Haircare Essential | G39: Beauty & Personal Care | H39: Haircare | I39: Pinecrest | J39: CUST001315 | K39: 2026-06-05 | L39: Online | M39: Completed
A40: OI529577 | B40: ORD118514 | C40: PROD1109 | D40: 4 | F40: Vertex Decor Max | G40: Home & Kitchen | H40: Decor | I40: Vertex | J40: CUST000743 | K40: 2025-09-03 | L40: In-Store | M40: Completed
A41: OI554265 | B41: ORD114522 | C41: PROD1140 | D41: 3 | E41: 629.46 | F41: TrueForm Furniture Classic | G41: Home & Kitchen | H41: Furniture | I41: TrueForm | J41: CUST003690 | K41: 2025-11-20 | L41: In-Store | M41: Completed
A42: OI512680 | B42: ORD105058 | C42: PROD1128 | D42: 1 | E42: 876.84 | F42: Pinecrest Haircare Lite | G42: Beauty & Personal Care | H42: Haircare | I42: Pinecrest | J42: CUST003644 | K42: 2026-01-11 | L42: Online | M42: Completed
A43: OI528901 | B43: ORD122252 | C43: PROD1186 | D43: 2 | E43: 91.47 | F43: Lumen Smart Home | G43: Electronics | H43: Smart Home | I43: Lumen | J43: CUST005202 | K43: 2025-07-25 | L43: Online | M43: Returned
A44: OI549605 | B44: ORD112541 | C44: PROD1035 | D44: 1 | E44: 489.75 | F44: Meridian Basics Women's Clothing Pro | G44: Apparel | H44: Women's Clothing | I44: Meridian Basics | J44: CUST005791 | K44: 2026-03-10 | L44: Online | M44: Completed
A45: OI528722 | B45: ORD108696 | C45: PROD1187 | D45: 1 | E45: 57.19 | F45: Meridian Basics Fitness Equipment Classic | G45: Sports & Outdoors | H45: Fitness Equipment | I45: Meridian Basics | J45: CUST005743 | K45: 2026-04-16 | L45: Mobile App | M45: COMPLETED
A46: OI569949 | B46: ORD126210 | C46: PROD1133 | D46: 1 | E46: 657.83 | F46: Meridian Basics Smart Home Essential | G46: Electronics | H46: Smart Home | I46: Meridian Basics | J46: CUST000126 | K46: 2024-03-23 | L46: Mobile App | M46: Completed
A47: OI559224 | B47: ORD103817 | C47: PROD1095 | D47: 1 | E47: 106.61 | F47: Sabre Cycling X | G47: Sports & Outdoors | H47: Cycling | I47: Sabre | J47: CUST004084 | K47: 2023-04-21 | L47: Mobile App | M47: Completed
A48: OI519731 | B48: ORD120516 | C48: PROD1128 | D48: 2 | E48: 869.4 | F48: Pinecrest Haircare Lite | G48: Beauty & Personal Care | H48: Haircare | I48: Pinecrest | J48: CUST000457 | K48: 2026-06-03 | L48: Mobile App | M48: Completed
A49: OI554521 | B49: ORD115310 | C49: PROD1015 | D49: 1 | E49: 379.13 | F49: Lumen Cookware Lite | G49: Home & Kitchen | H49: Cookware | I49: Lumen | J49: CUST002357 | K49: 2026-01-08 | L49: Online | M49: Cancelled
A50: OI511425 | B50: ORD116255 | C50: PROD1165 | D50: 1 | E50: 348.8 | F50: Solstice Smartphones Plus | G50: Electronics | H50: Smartphones | I50: Solstice | J50: CUST000082 | K50: 2026-04-08 | L50: Online | M50: Completed
A51: OI556807 | B51: ORD115207 | C51: PROD1209 | D51: 1 | E51: 654.81 | F51: Northfield Women's Clothing Lite | G51: Apparel | H51: Women's Clothing | I51: Northfield | J51: CUST001879 | K51: 2024-09-22 | L51: In-Store | M51: completed
A52: OI506530 | B52: ORD119893 | C52: PROD1077 | D52: 1 | E52: 646.09 | F52: TrueForm Women's Clothing Max | G52: Apparel | H52: Women's Clothing | I52: TrueForm | J52: CUST005716 | K52: 2026-01-19 | L52: Online | M52: Pending
... A55: OI559647 | B55: ORD115661 | C55: PROD1094 | D55: 2 | E55: 343.71 | F55: Lumen Women's Clothing Classic | G55: Apparel | H55: Women's Clothing | I55: Lumen | J55: CUST004054 | K55: 2025-08-06 | L55: In-Store | M55: Completed
A56: OI527662 | B56: ORD121895 | C56: PROD1012 | D56: 2 | F56: Northfield Cycling Lite | G56: Sports & Outdoors | H56: Cycling | I56: Northfield | J56: CUST000670 | K56: 2025-07-30 | L56: Mobile App | M56: Completed
A57: OI542769 | B57: ORD124235 | C57: PROD1097 | D57: 1 | E57: 251.04 | F57: BrightPath Accessories Plus | G57: Apparel | H57: Accessories | I57: BrightPath | J57: CUST003734 | K57: 2025-08-21 | L57: Mobile App | M57: Completed
A58: OI505245 | B58: ORD109973 | C58: PROD1126 | D58: 1 | E58: 600.34 | F58: Orion Laptops Essential | G58: Electronics | H58: Laptops | I58: Orion | J58: CUST002084 | K58: 2025-10-10 | L58: Mobile App | M58: Completed
A59: OI547743 | B59: ORD101716 | C59: PROD1045 | D59: 1 | E59: 116.65 | F59: Sabre Furniture | G59: Home & Kitchen | H59: Furniture | I59: Sabre | J59: CUST003035 | K59: 2026-03-30 | L59: In-Store | M59: Completed
A60: OI536586 | B60: ORD104480 | C60: PROD1174 | D60: 1 | E60: 331.83 | F60: TrueForm Tablet | G60: Electronics | H60: Tablets | I60: TrueForm | J60: CUST001871 | K60: 2024-06-11 | L60: In-Store | M60: Completed
A61: OI501685 | B61: ORD119580 | C61: PROD1013 | D61: 1 | E61: 166.51 | F61: TrueForm Fragrance | G61: Beauty & Personal Care | H61: Fragrance | I61: TrueForm | J61: CUST003443 | K61: 2025-03-09 | L61: Mobile App | M61: Completed
A62: OI504903 | B62: ORD118748 | C62: PROD1150 | D62: 1 | E62: 51.07 | F62: Pinecrest Skincare Classic | G62: Beauty & Personal Care | H62: Skincare | I62: Pinecrest | J62: CUST003723 | K62: 2024-12-10 | L62: Online | M62: Completed
A63: OI555894 | B63: ORD117781 | C63: PROD1024 | D63: 1 | E63: 335.28 | F63: Pinecrest Skincare Classic | G63: Beauty & Personal Care | H63: Skincare | I63: Pinecrest | J63: CUST003107 | K63: 2025-01-24 | L63: Online | M63: Completed
A64: OI551522 | B64: ORD107102 | C64: PROD1031 | D64: 1 | E64: 593.48 | F64: Lumen Cookware Essential | G64: Home & Kitchen | H64: Cookware | I64: Lumen | J64: CUST005612 | K64: 2023-10-04 | L64: In-Store | M64: COMPLETED
A65: OI508042 | B65: ORD123000 | C65: PROD1006 | D65: 3 | E65: 526.81 | F65: Crestline Decor | G65: Home & Kitchen | H65: Decor | I65: Crestline | J65: CUST002434 | K65: 2022-05-08 | L65: In-Store | M65: Completed
A66: OI538826 | B66: ORD103387 | C66: PROD1204 | D66: 1 | E66: 516.67 | F66: Lumen Small Appliance X | G66: Home & Kitchen | H66: Small Appliances | I66: Lumen | J66: CUST004681 | K66: 2025-04-09 | L66: Mobile App | M66: Completed
A67: OI533660 | B67: ORD123574 | C67: PROD1125 | D67: 1 | E67: 221.84 | F67: Northfield Team Sports Pro | G67: Sports & Outdoors | H67: Team Sports | I67: Northfield | J67: CUST005151 | K67: 2026-02-21 | L67: Online | M67: Completed
A68: OI566074 | B68: ORD112569 | C68: PROD1124 | D68: 1 | E68: 983.14 | F68: Crestline Smart Home Essential | G68: Electronics | H68: Smart Home | I68: Crestline | J68: CUST001222 | K68: 2024-06-30 | L68: Online | M68: completed
A69: OI549349 | B69: ORD107402 | C69: PROD1117 | D69: 1 | E69: 186.88 | F69: Orion Men's Clothing Max | G69: Apparel | I69: Orion | J69: CUST000157 | K69: 2024-05-26 | L69: Online | M69: Completed
A70: OI527768 | B70: ORD118859 | C70: PROD1128 | D70: 3 | E70: 843.03 | F70: Pinecrest Haircare Lite | G70: Beauty & Personal Care | H70: Haircare | I70: Pinecrest | J70: CUST004189 | K70: 2025-06-24 | L70: Mobile App | M70: Completed
A71: OI500760 | B71: ORD111271 | C71: PROD1101 | D71: 2 | E71: 171.61 | F71: Pinecrest Camping Lite | G71: Sports & Outdoors | I71: Pinecrest | J71: CUST005473 | K71: 2025-07-11 | L71: Mobile App | M71: Completed
A72: OI505343 | B72: ORD103483 | C72: PROD1016 | D72: 3 | E72: 79.81 | F72: Orion Fitness Equipment Max | G72: Sports & Outdoors | H72: Fitness Equipment | I72: Orion | J72: CUST000646 | K72: 2025-08-07 | L72: Mobile App | M72: Completed
A73: OI541617 | B73: ORD126876 | C73: PROD1033 | D73: 1 | E73: 142.9 | F73: Crestline Wellness Classic | G73: Beauty & Personal Care | H73: Wellness | I73: Crestline | J73: CUST004197 | K73: 2024-09-04 | L73: Mobile App | M73: Completed
A74: OI542059 | B74: ORD122353 | C74: PROD1100 | D74: 1 | E74: 352.64 | F74: Cadence Cycling Plus | G74: Sports & Outdoors | H74: Cycling | I74: Cadence | J74: CUST002631 | K74: 2024-05-11 | L74: Mobile App | M74: Completed
A75: OI511154 | B75: ORD125270 | C75: PROD1033 | D75: 2 | E75: 146.37 | F75: Crestline Wellness Classic | G75: Beauty & Personal Care | H75: Wellness | I75: Crestline | J75: CUST004785 | K75: 2025-12-01 | L75: In-Store | M75: Completed
A76: OI534507 | B76: ORD104776 | C76: PROD1134 | D76: 1 | E76: 251.17 | F76: Meridian Basics Cycling Essential | G76: Sports & Outdoors | H76: Cycling | I76: Meridian Basics | J76: CUST004929 | K76: 2022-06-07 | L76: Online | M76: Completed
A77: OI507811 | B77: ORD111767 | C77: PROD1176 | D77: 1 | E77: 403.04 | F77: Amberly Fragrance Essential | G77: Beauty & Personal Care | H77: Fragrance | I77: Amberly | J77: CUST001550 | K77: 2025-12-04 | L77: Online | M77: Completed
A78: OI572963 | B78: ORD106229 | C78: PROD1157 | D78: 1 | E78: 746.27 | F78: Amberly Team Sports Plus | G78: Sports & Outdoors | H78: Team Sports | I78: Amberly | J78: CUST004476 | K78: 2024-05-23 | L78: Online | M78: Completed
A79: OI538844 | B79: ORD106593 | C79: PROD1039 | D79: 1 | E79: 207.84 | F79: Meridian Basics Smartphones X | G79: Electronics | H79: Smartphones | I79: Meridian Basics | J79: CUST005021 | K79: 2026-05-30 | L79: In-Store | M79: completed
A80: OI535703 | B80: ORD121548 | C80: PROD1033 | D80: 1 | E80: 147.98 | F80: Crestline Wellness Classic | G80: Beauty & Personal Care | H80: Wellness | I80: Crestline | J80: CUST005884 | K80: 2025-11-14 | L80: Mobile App | M80: Completed
A81: OI563754 | B81: ORD112704 | C81: PROD1023 | D81: 2 | E81: 260.4 | F81: BrightPath Fragrance Max | G81: Beauty & Personal Care | H81: Fragrance | I81: BrightPath | J81: CUST005444 | K81: 2026-05-18 | L81: Online | M81: Completed
A82: OI569048 | B82: ORD115184 | C82: PROD1045 | D82: 2 | E82: 120.1 | F82: Sabre Furniture | G82: Home & Kitchen | H82: Furniture | I82: Sabre | J82: CUST000614 | K82: 2025-10-29 | L82: Online | M82: Completed
A83: OI534585 | B83: ORD124870 | C83: PROD1193 | D83: 4 | E83: 179.19 | F83: Crestline Wellness | G83: Beauty & Personal Care | H83: Wellness | I83: Crestline | J83: CUST004885 | K83: 2024-09-18 | L83: In-Store | M83: Completed
... A100: OI526515 | B100: ORD104427 | C100: PROD1029 | D100: 3 | E100: 37.86 | F100: Northfield Fragrance Pro | G100: Beauty & Personal Care | H100: Fragrance | I100: Northfield | J100: CUST000542 | K100: 2021-09-28 | L100: In-Store | M100: Completed
A101: OI502019 | B101: ORD111967 | C101: PROD1205 | D101: 2 | E101: 342.07 | F101: Sabre Cameras Classic | G101: Electronics | I101: Sabre | J101: CUST005235 | K101: 2023-11-08 | L101: In-Store | M101: Completed
A102: OI568329 | B102: ORD103372 | C102: PROD1213 | D102: 1 | E102: 462.49 | F102: Amberly Smartphone X | G102: Electronics | H102: Smartphones | I102: Amberly | J102: CUST003830 | K102: 2025-03-04 | L102: Online | M102: Completed
A103: OI569269 | B103: ORD117105 | C103: PROD1058 | D103: 1 | E103: 500.21 | F103: Nova Accessories | G103: Apparel | H103: Accessories | I103: Nova | J103: CUST000956 | K103: 2026-03-13 | L103: Mobile App | M103: Completed
A104: OI566697 | B104: ORD107454 | C104: PROD1160 | D104: 4 | E104: 505.92 | F104: Amberly Wellness Pro | G104: Beauty & Personal Care | H104: Wellness | I104: Amberly | J104: CUST000209 | K104: 2026-01-03 | L104: Mobile App | M104: Completed
A105: OI519407 | B105: ORD100470 | C105: PROD1135 | D105: 3 | E105: 812.34 | F105: Everwood Furniture X | G105: Home & Kitchen | H105: Furniture | I105: Everwood | J105: CUST000055 | K105: 2024-04-15 | L105: In-Store | M105: Cancelled
A106: OI554612 | B106: ORD116189 | C106: PROD1144 | D106: 1 | E106: 255.96 | F106: Amberly Camping Pro | G106: Sports & Outdoors | H106: Camping | I106: Amberly | J106: CUST002508 | K106: 2023-04-25 | L106: Online | M106: Completed
A107: OI563495 | B107: ORD118875 | C107: PROD1112 | D107: 2 | E107: 180.02 | F107: Meridian Basics Footwear Pro | G107: Apparel | H107: Footwear | I107: Meridian Basics | J107: CUST001735 | K107: 2026-04-26 | L107: Mobile App | M107: Completed
A108: OI540202 | B108: ORD115354 | C108: PROD1130 | D108: 1 | E108: 687.75 | F108: Nova Haircare | G108: Beauty & Personal Care | I108: Nova | J108: CUST003010 | K108: 2023-12-09 | L108: Online | M108: Completed
A109: OI551111 | B109: ORD115610 | C109: PROD1024 | D109: 2 | E109: 331.49 | F109: Pinecrest Skincare Classic | G109: Beauty & Personal Care | H109: Skincare | I109: Pinecrest | J109: CUST001994 | K109: 2026-06-23 | L109: Mobile App | M109: Cancelled
A110: OI526973 | B110: ORD112452 | C110: PROD1139 | D110: 1 | E110: 696.62 | F110: Meridian Basics Men's Clothing | G110: Apparel | H110: Men's Clothing | I110: Meridian Basics | J110: CUST005631 | K110: 2025-06-05 | L110: Mobile App | M110: Completed
A111: OI540335 | B111: ORD101864 | C111: PROD1139 | D111: 3 | E111: 681.27 | F111: Meridian Basics Men's Clothing | G111: Apparel | H111: Men's Clothing | I111: Meridian Basics | J111: CUST001442 | K111: 2024-10-20 | L111: Mobile App | M111: Completed
A112: OI503651 | B112: ORD110156 | C112: PROD1179 | D112: 1 | E112: 777.84 | F112: Meridian Basics Wellness Lite | G112: Beauty & Personal Care | H112: Wellness | I112: Meridian Basics | J112: CUST004861 | K112: 2025-02-02 | L112: Online | M112: Completed
A113: OI539173 | B113: ORD106191 | C113: PROD1170 | D113: 1 | E113: 382.01 | F113: Cadence Accessories Max | G113: Apparel | H113: Accessories | I113: Cadence | J113: CUST001345 | K113: 2024-01-24 | L113: Mobile App | M113: Completed
A114: OI512456 | B114: ORD127601 | C114: PROD1112 | D114: 1 | E114: 176.07 | F114: Meridian Basics Footwear Pro | G114: Apparel | H114: Footwear | I114: Meridian Basics | J114: CUST004007 | K114: 2021-08-02 | L114: Mobile App | M114: Completed
A115: OI549975 | B115: ORD109599 | C115: PROD1101 | D115: 1 | E115: 177.63 | F115: Pinecrest Camping Lite | G115: Sports & Outdoors | I115: Pinecrest | J115: CUST003157 | K115: 2026-04-03 | L115: In-Store | M115: Completed
A116: OI566190 | B116: ORD107056 | C116: PROD1209 | D116: 1 | E116: 624.75 | F116: Northfield Women's Clothing Lite | G116: Apparel | H116: Women's Clothing | I116: Northfield | J116: CUST003375 | K116: 2025-04-21 | L116: Mobile App | M116: Completed
A117: OI507439 | B117: ORD117261 | C117: PROD1215 | D117: 1 | E117: 143.86 | F117: Northfield Women's Clothing Pro | G117: Apparel | H117: Women's Clothing | I117: Northfield | J117: CUST004341 | K117: 2026-05-01 | L117: Mobile App | M117: Completed
A118: OI539074 | B118: ORD126020 | C118: PROD1157 | D118: 1 | E118: 755.77 | F118: Amberly Team Sports Plus | G118: Sports & Outdoors | H118: Team Sports | I118: Amberly | J118: CUST002600 | K118: 2022-10-24 | L118: Online | M118: Completed
A119: OI512348 | B119: ORD110500 | C119: PROD1190 | D119: 3 | E119: 118.95 | F119: Amberly Camping Max | G119: Sports & Outdoors | H119: Camping | I119: Amberly | J119: CUST000895 | K119: 2023-08-09 | L119: Mobile App | M119: Completed
A120: OI567024 | B120: ORD114571 | C120: PROD1052 | D120: 1 | E120: 579.57 | F120: Orion Haircare Essential | G120: Beauty & Personal Care | H120: Haircare | I120: Orion | J120: CUST001558 | K120: 2023-06-26 | L120: In-Store | M120: Completed
A121: OI517144 | B121: ORD103228 | C121: PROD1047 | D121: 1 | E121: 620.69 | F121: Solstice Footwear Classic | G121: Apparel | H121: Footwear | I121: Solstice | J121: CUST003653 | K121: 2025-11-27 | L121: Mobile App | M121: Completed
A122: OI542245 | B122: ORD107580 | C122: PROD1036 | D122: 1 | E122: 15.48 | F122: Amberly Bedding Max | G122: Home & Kitchen | H122: Bedding | I122: Amberly | J122: CUST000029 | K122: 2023-10-07 | L122: Mobile App | M122: Completed
A123: OI510783 | B123: ORD124630 | C123: PROD1187 | D123: 1 | E123: 55.21 | F123: Meridian Basics Fitness Equipment Classic | G123: Sports & Outdoors | H123: Fitness Equipment | I123: Meridian Basics | J123: CUST000032 | K123: 2026-03-21 | L123: Online | M123: Completed
A124: OI545647 | B124: ORD115968 | C124: PROD1050 | D124: 2 | E124: 35.52 | F124: TrueForm Bedding Essential | G124: Home & Kitchen | H124: Bedding | I124: TrueForm | J124: CUST005946 | K124: 2022-10-20 | L124: In-Store | M124: Pending
A125: OI540111 | B125: ORD116028 | C125: PROD1109 | D125: 2 | E125: 663.93 | F125: Vertex Decor Max | G125: Home & Kitchen | H125: Decor | I125: Vertex | J125: CUST001160 | K125: 2021-05-25 | L125: Online | M125: Completed
A126: OI504454 | B126: ORD101173 | C126: PROD1059 | D126: 2 | E126: 736.07 | F126: Lumen Team Sports Lite | G126: Sports & Outdoors | H126: Team Sports | I126: Lumen | J126: CUST005871 | K126: 2025-05-27 | L126: In-Store | M126: Completed
A127: OI525051 | B127: ORD124960 | C127: PROD1022 | D127: 1 | E127: 242.82 | F127: Sabre Smart Home Max | G127: Electronics | H127: Smart Home | I127: Sabre | J127: CUST000064 | K127: 2025-07-25 | L127: In-Store | M127: Completed
... A146: OI500856 | B146: ORD117313 | C146: PROD1099 | D146: 2 | E146: 874.33 | F146: Orion Tablet | G146: Electronics | H146: Tablets | I146: Orion | J146: CUST004532 | K146: 2022-06-30 | L146: In-Store | M146: Completed
A147: OI526635 | B147: ORD119709 | C147: PROD1162 | D147: 1 | E147: 893.83 | F147: Crestline Smart Home Pro | G147: Electronics | I147: Crestline | J147: CUST000113 | K147: 2024-04-05 | L147: Online | M147: Completed
A148: OI572197 | B148: ORD117367 | C148: PROD1193 | D148: 3 | E148: 174.9 | F148: Crestline Wellness | G148: Beauty & Personal Care | H148: Wellness | I148: Crestline | J148: CUST000898 | K148: 2024-04-06 | L148: In-Store | M148: Completed
A149: OI542831 | B149: ORD113234 | C149: PROD1093 | D149: 2 | E149: 694.9 | F149: TrueForm Small Appliances Pro | G149: Home & Kitchen | H149: Small Appliances | I149: TrueForm | J149: CUST001009 | K149: 2021-08-08 | L149: In-Store | M149: Completed
A150: OI518583 | B150: ORD127492 | C150: PROD1067 | D150: 1 | E150: 667.25 | F150: Nova Smart Home Max | G150: Electronics | H150: Smart Home | I150: Nova | J150: CUST003001 | K150: 2024-07-03 | L150: Online | M150: Completed
A151: OI529645 | B151: ORD101790 | C151: PROD1006 | D151: 1 | E151: 514.84 | F151: Crestline Decor | G151: Home & Kitchen | H151: Decor | I151: Crestline | J151: CUST004569 | K151: 2026-03-28 | L151: Mobile App | M151: Completed
A152: OI544039 | B152: ORD114806 | C152: PROD1199 | D152: 1 | F152: Orion Smartphones Essential | G152: Electronics | H152: Smartphones | I152: Orion | J152: CUST003490 | K152: 2026-05-15 | L152: Online | M152: Completed
A153: OI559113 | B153: ORD113666 | C153: PROD1010 | D153: 4 | E153: 364.69 | F153: Cadence Wellnes X | G153: Beauty & Personal Care | H153: Wellness | I153: Cadence | J153: CUST000802 | K153: 2025-03-03 | L153: Online | M153: Completed
A154: OI566616 | B154: ORD124629 | C154: PROD1095 | D154: 2 | E154: 103.4 | F154: Sabre Cycling X | G154: Sports & Outdoors | H154: Cycling | I154: Sabre | J154: CUST000032 | K154: 2026-05-18 | L154: In-Store | M154: Completed
A155: OI557220 | B155: ORD100483 | C155: PROD1047 | D155: 2 | E155: 605.23 | F155: Solstice Footwear Classic | G155: Apparel | H155: Footwear | I155: Solstice | J155: CUST001411 | K155: 2025-04-28 | L155: Mobile App | M155: Completed
A156: OI563332 | B156: ORD111427 | C156: PROD1216 | D156: 1 | E156: 354.55 | F156: Northfield Women's Clothing Plus | G156: Apparel | H156: Women's Clothing | I156: Northfield | J156: CUST002864 | K156: 2025-11-20 | L156: In-Store | M156: Completed
A157: OI543067 | B157: ORD101423 | C157: PROD1219 | D157: 1 | E157: 389.5 | F157: Orion Cycling Max | G157: Sports & Outdoors | H157: Cycling | I157: Orion | J157: CUST005852 | K157: 2023-01-14 | L157: In-Store | M157: Completed
A158: OI538417 | B158: ORD108341 | C158: PROD1195 | D158: 4 | E158: 755.74 | F158: Meridian Basics Headphones Plus | G158: Electronics | H158: Headphones | I158: Meridian Basics | J158: CUST003785 | K158: 2025-02-26 | L158: In-Store | M158: Completed
A159: OI510971 | B159: ORD128211 | C159: PROD1031 | D159: 2 | E159: 606.99 | F159: Lumen Cookware Essential | G159: Home & Kitchen | H159: Cookware | I159: Lumen | J159: CUST002299 | K159: 2022-06-18 | L159: Online | M159: Completed
A160: OI541695 | B160: ORD120658 | C160: PROD1083 | D160: 3 | E160: 202.54 | F160: BrightPath Smart Home Pro | G160: Electronics | H160: Smart Home | I160: BrightPath | J160: CUST002699 | K160: 2026-04-04 | L160: Online | M160: Cancelled
A161: OI521025 | B161: ORD114585 | C161: PROD1049 | D161: 1 | E161: 19.62 | F161: Vertex Small Appliances X | G161: Home & Kitchen | H161: Small Appliances | I161: Vertex | J161: CUST005432 | K161: 2025-08-04 | L161: In-Store | M161: Completed
...

Sheet Orders_Clean
A1: order_id | B1: customer_id | C1: order_date | D1: channel | E1: order_status | F1: payment_method | G1: shipping_cost | H1: discount_pct | I1: total_amount | J1: first_name | K1: last_name | L1: state | M1: membership_tier | N1: signup_date | O1: first_name_clean | P1: last_name_clean | Q1: membership_tier_clean | R1: state_clean | S1: order_date_status
A2: ORD127194 | B2: CUST001908 | C2: 2025-05-31 | D2: In-Store | E2: Completed | F2: PayPal | G2: 5.99 | H2: 0 | I2: 607.63 | J2: Ashley | K2: Hester | L2: Indiana | M2: BRONZE | N2: 05/18/2025 | O2: =IF(J2="","UNKNOWN",PROPER(TRIM(J2))) -> Ashley | P2: =IF(K2="","UNKNOWN",PROPER(TRIM(K2))) -> Hester | Q2: =IF(M2="","UNKNOWN",PROPER(TRIM(M2))) -> Bronze | R2: =IFERROR(VLOOKUP(TRIM(L2),State_Mapping!A:B,2,FALSE),"Unknown") -> Indiana | S2: =IF(C2="","Missing","Valid") -> Valid
A3: ORD109227 | B3: CUST004626 | C3: 2025-08-22 | D3: Mobile App | E3: Returned | F3: Gift Card | G3: 0 | H3: 15 | I3: 1195.8 | J3: Leah | K3: Whitaker | L3: WISCONSIN | M3: gold | N3: 2024-03-22
A4: ORD109077 | B4: CUST000733 | C4: 2024-09-16 | D4: Online | E4: Cancelled | F4: Debit Card | G4: 4.99 | H4: 0 | I4: 2670.39 | J4: Bryan | K4: Holt | L4: GA | M4: Gold | N4: 2022-12-27
A5: ORD100396 | B5: CUST002155 | C5: 2025-04-14 | D5: Mobile App | E5: Pending | F5: Credit Card | G5: 0 | H5: 0 | I5: 2207.73 | J5: Dennis | K5: Rowe | L5: PA | M5: Bronze | N5: 2025-04-02
A6: ORD113973 | B6: CUST001459 | C6: 2023-10-12 | D6: Online | E6: Completed | F6: PayPal | G6: 0 | H6: 0 | I6: 755.59 | J6: Brett | K6: Ashley | L6: NY | M6: silver | N6: 2022-12-15 | O6: =IF(J6="","UNKNOWN",PROPER(TRIM(J6))) -> Brett | P6: =IF(K6="","UNKNOWN",PROPER(TRIM(K6))) -> Ashley | Q6: =IF(M6="","UNKNOWN",PROPER(TRIM(M6))) -> Silver | R6: =IFERROR(VLOOKUP(TRIM(L6),State_Mapping!A:B,2,FALSE),"Unknown") -> New York | S6: =IF(C6="","Missing","Valid") -> Valid
A7: ORD126188 | B7: CUST005599 | C7: 2023-07-19 | D7: Mobile App | E7: Pending | F7: Gift Card | G7: 4.99 | H7: 0 | I7: 608.18 | J7: Molly | K7: Serrano | L7: Wisconsin | M7: gold | N7: 2021-01-04
A8: ORD119947 | B8: CUST005844 | C8: 2026-05-04 | D8: Mobile App | E8: Completed | F8: Debit Card | G8: 0 | H8: 0 | I8: 2447.22 | J8: William | K8: Luna | L8: OH | M8: BRONZE | N8: 2024-08-31 | O8: =IF(J8="","UNKNOWN",PROPER(TRIM(J8))) -> William | P8: =IF(K8="","UNKNOWN",PROPER(TRIM(K8))) -> Luna | Q8: =IF(M8="","UNKNOWN",PROPER(TRIM(M8))) -> Bronze | R8: =IFERROR(VLOOKUP(TRIM(L8),State_Mapping!A:B,2,FALSE),"Unknown") -> Ohio | S8: =IF(C8="","Missing","Valid") -> Valid
A9: ORD116133 | B9: CUST001071 | C9: 2022-02-02 | D9: Online | E9: Completed | F9: Gift Card | G9: 0 | H9: 5 | I9: 1552.8 | J9: James | K9: Mullen | L9: Michigan | M9: Silver | N9: 2020-09-24 | O9: =IF(J9="","UNKNOWN",PROPER(TRIM(J9))) -> James | P9: =IF(K9="","UNKNOWN",PROPER(TRIM(K9))) -> Mullen | Q9: =IF(M9="","UNKNOWN",PROPER(TRIM(M9))) -> Silver | R9: =IFERROR(VLOOKUP(TRIM(L9),State_Mapping!A:B,2,FALSE),"Unknown") -> Michigan | S9: =IF(C9="","Missing","Valid") -> Valid
A10: ORD125114 | B10: CUST005141 | C10: 2026-03-10 | D10: Online | E10: Completed | F10: PayPal | G10: 12.99 | H10: 5 | I10: 458.04 | J10: Jose | K10: Owens | L10: New York | M10: Platinum | N10: 2026-03-05 | O10: =IF(J10="","UNKNOWN",PROPER(TRIM(J10))) -> Jose | P10: =IF(K10="","UNKNOWN",PROPER(TRIM(K10))) -> Owens | Q10: =IF(M10="","UNKNOWN",PROPER(TRIM(M10))) -> Platinum | R10: =IFERROR(VLOOKUP(TRIM(L10),State_Mapping!A:B,2,FALSE),"Unknown") -> New York | S10: =IF(C10="","Missing","Valid") -> Valid
A11: ORD103892 | B11: CUST004318 | C11: 2025-02-22 | D11: Online | E11: Completed | F11: Debit Card | G11: 12.99 | H11: 0 | I11: 130.99 | J11: Monica | K11: Williams | L11: NC | M11: BRONZE | N11: 2024-12-21 | O11: =IF(J11="","UNKNOWN",PROPER(TRIM(J11))) -> Monica | P11: =IF(K11="","UNKNOWN",PROPER(TRIM(K11))) -> Williams | Q11: =IF(M11="","UNKNOWN",PROPER(TRIM(M11))) -> Bronze | R11: =IFERROR(VLOOKUP(TRIM(L11),State_Mapping!A:B,2,FALSE),"Unknown") -> North Carolina | S11: =IF(C11="","Missing","Valid") -> Valid
A12: ORD118451 | B12: CUST004089 | C12: 2024-10-02 | D12: Online | E12: Completed | F12: Store Credit | G12: 0 | H12: 10 | I12: 1380.19 | J12: Laura | K12: Parrish | L12: Missouri | M12: Platinum | N12: 2022-08-31 | O12: =IF(J12="","UNKNOWN",PROPER(TRIM(J12))) -> Laura | P12: =IF(K12="","UNKNOWN",PROPER(TRIM(K12))) -> Parrish | Q12: =IF(M12="","UNKNOWN",PROPER(TRIM(M12))) -> Platinum | R12: =IFERROR(VLOOKUP(TRIM(L12),State_Mapping!A:B,2,FALSE),"Unknown") -> Missouri | S12: =IF(C12="","Missing","Valid") -> Valid
A13: ORD107271 | B13: CUST004048 | C13: 2024-01-09 | D13: Mobile App | E13: Completed | F13: Store Credit | G13: 7.99 | H13: 0 | I13: 944.14 | J13: Eric | K13: Mosley | L13: tx | M13: BRONZE | N13: 2020-10-21 | O13: =IF(J13="","UNKNOWN",PROPER(TRIM(J13))) -> Eric | P13: =IF(K13="","UNKNOWN",PROPER(TRIM(K13))) -> Mosley | Q13: =IF(M13="","UNKNOWN",PROPER(TRIM(M13))) -> Bronze | R13: =IFERROR(VLOOKUP(TRIM(L13),State_Mapping!A:B,2,FALSE),"Unknown") -> Texas | S13: =IF(C13="","Missing","Valid") -> Valid
A14: ORD117530 | B14: CUST000728 | C14: 2026-05-06 | D14: Mobile App | E14: Completed | F14: Credit Card | G14: 4.99 | H14: 20 | I14: 2023.4 | J14: Karen | K14: Scott | L14: CA | M14: bronze | N14: 2025-11-24 | O14: =IF(J14="","UNKNOWN",PROPER(TRIM(J14))) -> Karen | P14: =IF(K14="","UNKNOWN",PROPER(TRIM(K14))) -> Scott | Q14: =IF(M14="","UNKNOWN",PROPER(TRIM(M14))) -> Bronze | R14: =IFERROR(VLOOKUP(TRIM(L14),State_Mapping!A:B,2,FALSE),"Unknown") -> California | S14: =IF(C14="","Missing","Valid") -> Valid
A15: ORD105436 | B15: CUST000786 | C15: 2025-04-28 | D15: Online | E15: Completed | F15: Gift Card | G15: 7.99 | H15: 0 | I15: 1390.77 | J15: Bradley | K15: Cook | L15: Tennessee | M15: silver | N15: 2024-04-28 | O15: =IF(J15="","UNKNOWN",PROPER(TRIM(J15))) -> Bradley | P15: =IF(K15="","UNKNOWN",PROPER(TRIM(K15))) -> Cook | Q15: =IF(M15="","UNKNOWN",PROPER(TRIM(M15))) -> Silver | R15: =IFERROR(VLOOKUP(TRIM(L15),State_Mapping!A:B,2,FALSE),"Unknown") -> Tennessee | S15: =IF(C15="","Missing","Valid") -> Valid
A16: ORD123730 | B16: CUST002398 | C16: 2026-05-06 | D16: Online | E16: Completed | F16: Gift Card | G16: 0 | H16: 0 | I16: 3999.73 | J16: Matthew | K16: Blake | L16: AZ | M16: Bronze | N16: 2026-05-03 | O16: =IF(J16="","UNKNOWN",PROPER(TRIM(J16))) -> Matthew | P16: =IF(K16="","UNKNOWN",PROPER(TRIM(K16))) -> Blake | Q16: =IF(M16="","UNKNOWN",PROPER(TRIM(M16))) -> Bronze | R16: =IFERROR(VLOOKUP(TRIM(L16),State_Mapping!A:B,2,FALSE),"Unknown") -> Arizona | S16: =IF(C16="","Missing","Valid") -> Valid
A17: ORD121263 | B17: CUST003036 | C17: 2026-04-08 | D17: Mobile App | E17: Completed | F17: PayPal | G17: 4.99 | H17: 10 | I17: 1576.7 | J17: Frank | K17: Young | L17: MASSACHUSETTS | M17: BRONZE | N17: 2023-07-12 | O17: =IF(J17="","UNKNOWN",PROPER(TRIM(J17))) -> Frank | P17: =IF(K17="","UNKNOWN",PROPER(TRIM(K17))) -> Young | Q17: =IF(M17="","UNKNOWN",PROPER(TRIM(M17))) -> Bronze | R17: =IFERROR(VLOOKUP(TRIM(L17),State_Mapping!A:B,2,FALSE),"Unknown") -> Massachusetts | S17: =IF(C17="","Missing","Valid") -> Valid
A18: ORD110264 | B18: CUST001457 | C18: 2024-10-10 | D18: Mobile App | E18: COMPLETED | F18: Store Credit | G18: 5.99 | H18: 0 | I18: 2125.94 | J18: Danielle | K18: Kennedy | L18: Washington | M18: silver | N18: 2021-12-30 | O18: =IF(J18="","UNKNOWN",PROPER(TRIM(J18))) -> Danielle | P18: =IF(K18="","UNKNOWN",PROPER(TRIM(K18))) -> Kennedy | Q18: =IF(M18="","UNKNOWN",PROPER(TRIM(M18))) -> Silver | R18: =IFERROR(VLOOKUP(TRIM(L18),State_Mapping!A:B,2,FALSE),"Unknown") -> Washington | S18: =IF(C18="","Missing","Valid") -> Valid
A19: ORD106642 | B19: CUST004410 | C19: 2025-08-26 | D19: Mobile App | E19: Completed | F19: Debit Card | G19: 12.99 | H19: 20 | I19: 640.33 | J19: Shawn | K19: Norman | L19: NJ | M19: BRONZE | N19: 2022-10-04 | O19: =IF(J19="","UNKNOWN",PROPER(TRIM(J19))) -> Shawn | P19: =IF(K19="","UNKNOWN",PROPER(TRIM(K19))) -> Norman | Q19: =IF(M19="","UNKNOWN",PROPER(TRIM(M19))) -> Bronze | R19: =IFERROR(VLOOKUP(TRIM(L19),State_Mapping!A:B,2,FALSE),"Unknown") -> New Jersey | S19: =IF(C19="","Missing","Valid") -> Valid
A20: ORD100896 | B20: CUST004520 | C20: 2024-04-03 | D20: Mobile App | E20: Completed | F20: Store Credit | G20: 12.99 | H20: 0 | I20: 618.61 | J20: Bruce | K20: Brooks | L20: AZ | M20: GOLD | N20: 2021-06-26 | O20: =IF(J20="","UNKNOWN",PROPER(TRIM(J20))) -> Bruce | P20: =IF(K20="","UNKNOWN",PROPER(TRIM(K20))) -> Brooks | Q20: =IF(M20="","UNKNOWN",PROPER(TRIM(M20))) -> Gold | R20: =IFERROR(VLOOKUP(TRIM(L20),State_Mapping!A:B,2,FALSE),"Unknown") -> Arizona | S20: =IF(C20="","Missing","Valid") -> Valid
A21: ORD111349 | B21: CUST003485 | C21: 2022-12-21 | D21: Mobile App | E21: Returned | F21: PayPal | G21: 7.99 | H21: 15 | I21: 288.53 | J21: Dana | K21: Anderson | L21: Maryland | M21: Bronze | N21: 2022-10-09
A22: ORD102164 | B22: CUST005197 | C22: 2023-07-15 | D22: Online | E22: COMPLETED | F22: Gift Card | G22: 0 | H22: 0 | I22: 1502.65 | J22: Nicholas | K22: Reyes | L22: MASSACHUSETTS | M22: BRONZE | N22: 2021-04-05 | O22: =IF(J22="","UNKNOWN",PROPER(TRIM(J22))) -> Nicholas | P22: =IF(K22="","UNKNOWN",PROPER(TRIM(K22))) -> Reyes | Q22: =IF(M22="","UNKNOWN",PROPER(TRIM(M22))) -> Bronze | R22: =IFERROR(VLOOKUP(TRIM(L22),State_Mapping!A:B,2,FALSE),"Unknown") -> Massachusetts | S22: =IF(C22="","Missing","Valid") -> Valid
A23: ORD103099 | B23: CUST000943 | C23: 2026-03-24 | D23: In-Store | E23: Completed | F23: Store Credit | G23: 12.99 | H23: 0 | I23: 1462.85 | J23: Eric | K23: Hampton | L23: IN | M23: Gold | N23: 01/08/2023 | O23: =IF(J23="","UNKNOWN",PROPER(TRIM(J23))) -> Eric | P23: =IF(K23="","UNKNOWN",PROPER(TRIM(K23))) -> Hampton | Q23: =IF(M23="","UNKNOWN",PROPER(TRIM(M23))) -> Gold | R23: =IFERROR(VLOOKUP(TRIM(L23),State_Mapping!A:B,2,FALSE),"Unknown") -> Indiana | S23: =IF(C23="","Missing","Valid") -> Valid
A24: ORD101243 | B24: CUST001306 | C24: 2026-01-03 | D24: Mobile App | E24: Completed | F24: Credit Card | G24: 7.99 | H24: 0 | I24: 2336.59 | J24: Clarence | K24: Diaz | L24: MARYLAND | M24: Silver | N24: 2023-02-22 | O24: =IF(J24="","UNKNOWN",PROPER(TRIM(J24))) -> Clarence | P24: =IF(K24="","UNKNOWN",PROPER(TRIM(K24))) -> Diaz | Q24: =IF(M24="","UNKNOWN",PROPER(TRIM(M24))) -> Silver | R24: =IFERROR(VLOOKUP(TRIM(L24),State_Mapping!A:B,2,FALSE),"Unknown") -> Maryland | S24: =IF(C24="","Missing","Valid") -> Valid
A25: ORD104975 | B25: CUST003605 | C25: 2023-12-18 | D25: Mobile App | E25: Completed | F25: Gift Card | G25: 0 | H25: 0 | I25: 353.52 | J25: James | K25: George | L25: Illinois | M25: silver | N25: 2020-10-14 | O25: =IF(J25="","UNKNOWN",PROPER(TRIM(J25))) -> James | P25: =IF(K25="","UNKNOWN",PROPER(TRIM(K25))) -> George | Q25: =IF(M25="","UNKNOWN",PROPER(TRIM(M25))) -> Silver | R25: =IFERROR(VLOOKUP(TRIM(L25),State_Mapping!A:B,2,FALSE),"Unknown") -> Illinois | S25: =IF(C25="","Missing","Valid") -> Valid
A26: ORD126798 | B26: CUST002862 | C26: 2022-09-24 | D26: In-Store | E26: Completed | F26: Credit Card | G26: 4.99 | H26: 0 | I26: 850.54 | J26: Amy | K26: Alvarez | L26: ga | M26: gold | N26: 2022-02-17 | O26: =IF(J26="","UNKNOWN",PROPER(TRIM(J26))) -> Amy | P26: =IF(K26="","UNKNOWN",PROPER(TRIM(K26))) -> Alvarez | Q26: =IF(M26="","UNKNOWN",PROPER(TRIM(M26))) -> Gold | R26: =IFERROR(VLOOKUP(TRIM(L26),State_Mapping!A:B,2,FALSE),"Unknown") -> Georgia | S26: =IF(C26="","Missing","Valid") -> Valid
A27: ORD112498 | B27: CUST000920 | C27: 2024-09-03 | D27: Mobile App | E27: Completed | F27: Debit Card | G27: 0 | H27: 5 | I27: 781.66 | J27: Samuel | K27: Ayala | L27: Tennessee | M27: silver | N27: 2022-02-01 | O27: =IF(J27="","UNKNOWN",PROPER(TRIM(J27))) -> Samuel | P27: =IF(K27="","UNKNOWN",PROPER(TRIM(K27))) -> Ayala | Q27: =IF(M27="","UNKNOWN",PROPER(TRIM(M27))) -> Silver | R27: =IFERROR(VLOOKUP(TRIM(L27),State_Mapping!A:B,2,FALSE),"Unknown") -> Tennessee | S27: =IF(C27="","Missing","Valid") -> Valid
A28: ORD107493 | B28: CUST003048 | C28: 2024-05-21 | D28: Online | E28: Completed | F28: Store Credit | G28: 12.99 | H28: 0 | I28: 284.68 | J28: Matthew | K28: Bond | L28: Tennessee | M28: Silver | N28: 2024-03-06 | O28: =IF(J28="","UNKNOWN",PROPER(TRIM(J28))) -> Matthew | P28: =IF(K28="","UNKNOWN",PROPER(TRIM(K28))) -> Bond | Q28: =IF(M28="","UNKNOWN",PROPER(TRIM(M28))) -> Silver | R28: =IFERROR(VLOOKUP(TRIM(L28),State_Mapping!A:B,2,FALSE),"Unknown") -> Tennessee | S28: =IF(C28="","Missing","Valid") -> Valid
A29: ORD107844 | B29: CUST001240 | C29: 2022-11-01 | D29: In-Store | E29: Completed | F29: Debit Card | G29: 4.99 | H29: 0 | I29: 1879.32 | J29: Nicholas | K29: Gilmore | L29: Massachusetts | M29: Platinum | N29: 2022-05-30 | O29: =IF(J29="","UNKNOWN",PROPER(TRIM(J29))) -> Nicholas | P29: =IF(K29="","UNKNOWN",PROPER(TRIM(K29))) -> Gilmore | Q29: =IF(M29="","UNKNOWN",PROPER(TRIM(M29))) -> Platinum | R29: =IFERROR(VLOOKUP(TRIM(L29),State_Mapping!A:B,2,FALSE),"Unknown") -> Massachusetts | S29: =IF(C29="","Missing","Valid") -> Valid
A30: ORD123697 | B30: CUST000969 | C30: 2025-09-20 | D30: Mobile App | E30: Completed | F30: Store Credit | G30: 0 | H30: 10 | I30: 1766.19 | J30: Emily | K30: Garcia | L30: IN | M30: PLATINUM | N30: 08/30/2023 | O30: =IF(J30="","UNKNOWN",PROPER(TRIM(J30))) -> Emily | P30: =IF(K30="","UNKNOWN",PROPER(TRIM(K30))) -> Garcia | Q30: =IF(M30="","UNKNOWN",PROPER(TRIM(M30))) -> Platinum | R30: =IFERROR(VLOOKUP(TRIM(L30),State_Mapping!A:B,2,FALSE),"Unknown") -> Indiana | S30: =IF(C30="","Missing","Valid") -> Valid
A31: ORD106948 | B31: CUST001175 | C31: 2025-08-12 | D31: In-Store | E31: Completed | F31: Gift Card | G31: 0 | H31: 20 | I31: 1024.38 | J31: Lisa | K31: Christian | L31: Texas | M31: silver | N31: 2025-08-07 | O31: =IF(J31="","UNKNOWN",PROPER(TRIM(J31))) -> Lisa | P31: =IF(K31="","UNKNOWN",PROPER(TRIM(K31))) -> Christian | Q31: =IF(M31="","UNKNOWN",PROPER(TRIM(M31))) -> Silver | R31: =IFERROR(VLOOKUP(TRIM(L31),State_Mapping!A:B,2,FALSE),"Unknown") -> Texas | S31: =IF(C31="","Missing","Valid") -> Valid
A32: ORD123520 | B32: CUST001013 | C32: 2024-03-14 | D32: Online | E32: Completed | F32: Debit Card | G32: 4.99 | H32: 5 | I32: 610.86 | J32: Heather | K32: Yates | L32: CALIFORNIA | M32: silver | N32: 2024-02-26 | O32: =IF(J32="","UNKNOWN",PROPER(TRIM(J32))) -> Heather | P32: =IF(K32="","UNKNOWN",PROPER(TRIM(K32))) -> Yates | Q32: =IF(M32="","UNKNOWN",PROPER(TRIM(M32))) -> Silver | R32: =IFERROR(VLOOKUP(TRIM(L32),State_Mapping!A:B,2,FALSE),"Unknown") -> California | S32: =IF(C32="","Missing","Valid") -> Valid
A33: ORD105124 | B33: CUST004742 | C33: 2021-12-27 | D33: Mobile App | E33: Completed | F33: Credit Card | G33: 7.99 | H33: 15 | I33: 1902.07 | J33: Rebecca | K33: Adams | L33: Florida | M33: silver | N33: 2021-05-12 | O33: =IF(J33="","UNKNOWN",PROPER(TRIM(J33))) -> Rebecca | P33: =IF(K33="","UNKNOWN",PROPER(TRIM(K33))) -> Adams | Q33: =IF(M33="","UNKNOWN",PROPER(TRIM(M33))) -> Silver | R33: =IFERROR(VLOOKUP(TRIM(L33),State_Mapping!A:B,2,FALSE),"Unknown") -> Florida | S33: =IF(C33="","Missing","Valid") -> Valid
... A49: ORD109448 | B49: CUST000481 | C49: 2025-05-28 | D49: In-Store | E49: Completed | F49: Store Credit | G49: 5.99 | H49: 0 | I49: 1119.98 | J49: Michael | K49: Hahn | L49: FL | M49: Gold | N49: 02/10/2022 | O49: =IF(J49="","UNKNOWN",PROPER(TRIM(J49))) -> Michael | P49: =IF(K49="","UNKNOWN",PROPER(TRIM(K49))) -> Hahn | Q49: =IF(M49="","UNKNOWN",PROPER(TRIM(M49))) -> Gold | R49: =IFERROR(VLOOKUP(TRIM(L49),State_Mapping!A:B,2,FALSE),"Unknown") -> Florida | S49: =IF(C49="","Missing","Valid") -> Valid
A50: ORD108364 | B50: CUST002465 | C50: 2026-04-27 | D50: In-Store | E50: Returned | F50: Gift Card | G50: 0 | H50: 0 | I50: 5899.92 | J50: Karen | K50: Bowers | L50: Michigan | M50: silver | N50: 2025-02-07
A51: ORD125370 | B51: CUST004218 | C51: 2025-03-16 | D51: In-Store | E51: Completed | F51: Gift Card | G51: 0 | H51: 0 | I51: 483.49 | J51: Heather | K51: Delacruz | L51: OH | M51: Gold | N51: 2025-03-16 | O51: =IF(J51="","UNKNOWN",PROPER(TRIM(J51))) -> Heather | P51: =IF(K51="","UNKNOWN",PROPER(TRIM(K51))) -> Delacruz | Q51: =IF(M51="","UNKNOWN",PROPER(TRIM(M51))) -> Gold | R51: =IFERROR(VLOOKUP(TRIM(L51),State_Mapping!A:B,2,FALSE),"Unknown") -> Ohio | S51: =IF(C51="","Missing","Valid") -> Valid
A52: ORD118155 | B52: CUST004880 | C52: 2024-07-25 | D52: Mobile App | E52: Completed | F52: Debit Card | G52: 0 | H52: 0 | I52: 1977.74 | J52: Christopher | K52: Thomas | L52: WA | M52: Bronze | N52: 2022-08-14 | O52: =IF(J52="","UNKNOWN",PROPER(TRIM(J52))) -> Christopher | P52: =IF(K52="","UNKNOWN",PROPER(TRIM(K52))) -> Thomas | Q52: =IF(M52="","UNKNOWN",PROPER(TRIM(M52))) -> Bronze | R52: =IFERROR(VLOOKUP(TRIM(L52),State_Mapping!A:B,2,FALSE),"Unknown") -> Washington | S52: =IF(C52="","Missing","Valid") -> Valid
A53: ORD119007 | B53: CUST004242 | C53: 2026-03-02 | D53: Mobile App | E53: Completed | F53: Credit Card | G53: 7.99 | H53: 0 | I53: 1132.23 | J53: Laura | K53: Johnson | L53: New York | M53: silver | N53: 2025-10-29 | O53: =IF(J53="","UNKNOWN",PROPER(TRIM(J53))) -> Laura | P53: =IF(K53="","UNKNOWN",PROPER(TRIM(K53))) -> Johnson | Q53: =IF(M53="","UNKNOWN",PROPER(TRIM(M53))) -> Silver | R53: =IFERROR(VLOOKUP(TRIM(L53),State_Mapping!A:B,2,FALSE),"Unknown") -> New York | S53: =IF(C53="","Missing","Valid") -> Valid
A54: ORD104400 | B54: CUST004958 | C54: 2023-10-28 | D54: Online | E54: Completed | F54: PayPal | G54: 12.99 | H54: 0 | I54: 1830.32 | J54: Isaiah | K54: Collins | L54: Missouri | M54: BRONZE | N54: 2023-01-11 | O54: =IF(J54="","UNKNOWN",PROPER(TRIM(J54))) -> Isaiah | P54: =IF(K54="","UNKNOWN",PROPER(TRIM(K54))) -> Collins | Q54: =IF(M54="","UNKNOWN",PROPER(TRIM(M54))) -> Bronze | R54: =IFERROR(VLOOKUP(TRIM(L54),State_Mapping!A:B,2,FALSE),"Unknown") -> Missouri | S54: =IF(C54="","Missing","Valid") -> Valid
A55: ORD101202 | B55: CUST001573 | C55: 2024-11-04 | D55: In-Store | E55: completed | F55: Gift Card | G55: 7.99 | H55: 0 | I55: 710.37 | J55: Angela | K55: Boyd | L55: md | M55: gold | N55: 2024-10-05 | O55: =IF(J55="","UNKNOWN",PROPER(TRIM(J55))) -> Angela | P55: =IF(K55="","UNKNOWN",PROPER(TRIM(K55))) -> Boyd | Q55: =IF(M55="","UNKNOWN",PROPER(TRIM(M55))) -> Gold | R55: =IFERROR(VLOOKUP(TRIM(L55),State_Mapping!A:B,2,FALSE),"Unknown") -> Massachusetts | S55: =IF(C55="","Missing","Valid") -> Valid
A56: ORD120538 | B56: CUST000877 | C56: 2025-08-28 | D56: In-Store | E56: Completed | F56: Debit Card | G56: 0 | H56: 0 | I56: 4777.65 | J56: Sandra | K56: Brewer | L56: AZ | M56: BRONZE | N56: 2025-08-26 | O56: =IF(J56="","UNKNOWN",PROPER(TRIM(J56))) -> Sandra | P56: =IF(K56="","UNKNOWN",PROPER(TRIM(K56))) -> Brewer | Q56: =IF(M56="","UNKNOWN",PROPER(TRIM(M56))) -> Bronze | R56: =IFERROR(VLOOKUP(TRIM(L56),State_Mapping!A:B,2,FALSE),"Unknown") -> Arizona | S56: =IF(C56="","Missing","Valid") -> Valid
A57: ORD109497 | B57: CUST005376 | C57: 2023-05-13 | D57: Mobile App | E57: Completed | F57: Credit Card | G57: 4.99 | H57: 15 | I57: 1133.91 | J57: Jessica | K57: Grant | L57: Tennessee | M57: Bronze | N57: 2023-03-24 | O57: =IF(J57="","UNKNOWN",PROPER(TRIM(J57))) -> Jessica | P57: =IF(K57="","UNKNOWN",PROPER(TRIM(K57))) -> Grant | Q57: =IF(M57="","UNKNOWN",PROPER(TRIM(M57))) -> Bronze | R57: =IFERROR(VLOOKUP(TRIM(L57),State_Mapping!A:B,2,FALSE),"Unknown") -> Tennessee | S57: =IF(C57="","Missing","Valid") -> Valid
A58: ORD121787 | B58: CUST003826 | C58: 2024-06-15 | D58: Online | E58: Completed | F58: Debit Card | G58: 7.99 | H58: 0 | I58: 48.37 | J58: Anna | K58: Lopez | L58: North Carolina | M58: Bronze | N58: 2023-11-23 | O58: =IF(J58="","UNKNOWN",PROPER(TRIM(J58))) -> Anna | P58: =IF(K58="","UNKNOWN",PROPER(TRIM(K58))) -> Lopez | Q58: =IF(M58="","UNKNOWN",PROPER(TRIM(M58))) -> Bronze | R58: =IFERROR(VLOOKUP(TRIM(L58),State_Mapping!A:B,2,FALSE),"Unknown") -> North Carolina | S58: =IF(C58="","Missing","Valid") -> Valid
A59: ORD124135 | B59: CUST004705 | C59: 2024-04-27 | D59: In-Store | E59: Cancelled | F59: Credit Card | G59: 4.99 | H59: 5 | I59: 1370.14 | J59: Sharon | K59: Ortiz | L59: California | M59: gold | N59: 2022-08-16
A60: ORD107926 | B60: CUST002081 | C60: 2023-11-27 | D60: In-Store | E60: Pending | F60: PayPal | G60: 5.99 | H60: 0 | I60: 1701.08 | J60: Randy | K60: Winters | L60: IN | M60: PLATINUM | N60: 2021-11-15
A61: ORD112891 | B61: CUST001963 | C61: 2022-04-28 | D61: Mobile App | E61: Completed | F61: Credit Card | G61: 0 | H61: 5 | I61: 537.65 | J61: Robert | K61: Davis | L61: in | M61: Platinum | N61: 2021-10-10 | O61: =IF(J61="","UNKNOWN",PROPER(TRIM(J61))) -> Robert | P61: =IF(K61="","UNKNOWN",PROPER(TRIM(K61))) -> Davis | Q61: =IF(M61="","UNKNOWN",PROPER(TRIM(M61))) -> Platinum | R61: =IFERROR(VLOOKUP(TRIM(L61),State_Mapping!A:B,2,FALSE),"Unknown") -> Indiana | S61: =IF(C61="","Missing","Valid") -> Valid
A62: ORD125643 | B62: CUST004467 | C62: 2026-04-06 | D62: In-Store | E62: Completed | F62: PayPal | G62: 0 | H62: 0 | I62: 3538.7 | J62: Carla | K62: Peck | L62: MI | M62: Bronze | N62: 2026-04-04 | O62: =IF(J62="","UNKNOWN",PROPER(TRIM(J62))) -> Carla | P62: =IF(K62="","UNKNOWN",PROPER(TRIM(K62))) -> Peck | Q62: =IF(M62="","UNKNOWN",PROPER(TRIM(M62))) -> Bronze | R62: =IFERROR(VLOOKUP(TRIM(L62),State_Mapping!A:B,2,FALSE),"Unknown") -> Michigan | S62: =IF(C62="","Missing","Valid") -> Valid
A63: ORD121646 | B63: CUST005085 | C63: 2024-10-24 | D63: Mobile App | E63: Completed | F63: Debit Card | G63: 4.99 | H63: 5 | I63: 305.44 | J63: Ashley | K63: Larson | L63: IN | M63: Bronze | N63: 2021-11-15 | O63: =IF(J63="","UNKNOWN",PROPER(TRIM(J63))) -> Ashley | P63: =IF(K63="","UNKNOWN",PROPER(TRIM(K63))) -> Larson | Q63: =IF(M63="","UNKNOWN",PROPER(TRIM(M63))) -> Bronze | R63: =IFERROR(VLOOKUP(TRIM(L63),State_Mapping!A:B,2,FALSE),"Unknown") -> Indiana | S63: =IF(C63="","Missing","Valid") -> Valid
A64: ORD107405 | B64: CUST000612 | C64: 2023-12-19 | D64: In-Store | E64: Completed | F64: PayPal | G64: 0 | H64: 0 | I64: 4188.75 | J64: Francisco | K64: Payne | L64: IN | M64: SILVER | N64: 2023-03-25 | O64: =IF(J64="","UNKNOWN",PROPER(TRIM(J64))) -> Francisco | P64: =IF(K64="","UNKNOWN",PROPER(TRIM(K64))) -> Payne | Q64: =IF(M64="","UNKNOWN",PROPER(TRIM(M64))) -> Silver | R64: =IFERROR(VLOOKUP(TRIM(L64),State_Mapping!A:B,2,FALSE),"Unknown") -> Indiana | S64: =IF(C64="","Missing","Valid") -> Valid
A65: ORD120855 | B65: CUST005573 | C65: 2025-05-22 | D65: In-Store | E65: Completed | F65: PayPal | G65: 4.99 | H65: 5 | I65: 1758.72 | J65: Lance | K65: Schultz | L65: MI | M65: PLATINUM | N65: 2021-05-07 | O65: =IF(J65="","UNKNOWN",PROPER(TRIM(J65))) -> Lance | P65: =IF(K65="","UNKNOWN",PROPER(TRIM(K65))) -> Schultz | Q65: =IF(M65="","UNKNOWN",PROPER(TRIM(M65))) -> Platinum | R65: =IFERROR(VLOOKUP(TRIM(L65),State_Mapping!A:B,2,FALSE),"Unknown") -> Michigan | S65: =IF(C65="","Missing","Valid") -> Valid
A66: ORD116978 | B66: CUST003424 | C66: 2022-12-16 | D66: Online | E66: Completed | F66: Store Credit | G66: 4.99 | H66: 15 | I66: 822.51 | J66: Thomas | K66: Mccall | L66: Arizona | M66: GOLD | N66: 2022-01-13 | O66: =IF(J66="","UNKNOWN",PROPER(TRIM(J66))) -> Thomas | P66: =IF(K66="","UNKNOWN",PROPER(TRIM(K66))) -> Mccall | Q66: =IF(M66="","UNKNOWN",PROPER(TRIM(M66))) -> Gold | R66: =IFERROR(VLOOKUP(TRIM(L66),State_Mapping!A:B,2,FALSE),"Unknown") -> Arizona | S66: =IF(C66="","Missing","Valid") -> Valid
A67: ORD126744 | B67: CUST005360 | C67: 2026-04-07 | D67: In-Store | E67: Completed | F67: Debit Card | G67: 5.99 | H67: 0 | I67: 811.73 | J67: Jennifer | K67: Cummings | L67: Florida | M67: bronze | N67: 2026-03-05 | O67: =IF(J67="","UNKNOWN",PROPER(TRIM(J67))) -> Jennifer | P67: =IF(K67="","UNKNOWN",PROPER(TRIM(K67))) -> Cummings | Q67: =IF(M67="","UNKNOWN",PROPER(TRIM(M67))) -> Bronze | R67: =IFERROR(VLOOKUP(TRIM(L67),State_Mapping!A:B,2,FALSE),"Unknown") -> Florida | S67: =IF(C67="","Missing","Valid") -> Valid
A68: ORD102358 | B68: CUST002855 | C68: 2023-02-27 | D68: Online | E68: Completed | F68: Credit Card | G68: 7.99 | H68: 25 | I68: 2401.36 | J68: Donald | K68: Rush | L68: NEW YORK | M68: BRONZE | N68: 2022-01-20 | O68: =IF(J68="","UNKNOWN",PROPER(TRIM(J68))) -> Donald | P68: =IF(K68="","UNKNOWN",PROPER(TRIM(K68))) -> Rush | Q68: =IF(M68="","UNKNOWN",PROPER(TRIM(M68))) -> Bronze | R68: =IFERROR(VLOOKUP(TRIM(L68),State_Mapping!A:B,2,FALSE),"Unknown") -> New York | S68: =IF(C68="","Missing","Valid") -> Valid
A69: ORD110940 | B69: CUST002974 | C69: 2022-12-22 | D69: Online | E69: Cancelled | F69: PayPal | G69: 4.99 | H69: 0 | I69: 1257.15 | J69: Michael | K69: Harris | L69: MO | M69: bronze | N69: 2022-07-31
A70: ORD106497 | B70: CUST002291 | C70: 2025-09-01 | D70: In-Store | E70: completed | F70: Gift Card | G70: 12.99 | H70: 0 | I70: 4164.32 | J70: Robert | K70: Herrera | L70: MO | M70: platinum | N70: 2023-08-24 | O70: =IF(J70="","UNKNOWN",PROPER(TRIM(J70))) -> Robert | P70: =IF(K70="","UNKNOWN",PROPER(TRIM(K70))) -> Herrera | Q70: =IF(M70="","UNKNOWN",PROPER(TRIM(M70))) -> Platinum | R70: =IFERROR(VLOOKUP(TRIM(L70),State_Mapping!A:B,2,FALSE),"Unknown") -> Missouri | S70: =IF(C70="","Missing","Valid") -> Valid
A71: ORD105370 | B71: CUST004814 | C71: 2023-08-14 | D71: Mobile App | E71: Completed | F71: Gift Card | G71: 7.99 | H71: 10 | I71: 1961.67 | J71: Pamela | K71: Oneal | L71: NORTH CAROLINA | M71: SILVER | N71: 2021-02-13 | O71: =IF(J71="","UNKNOWN",PROPER(TRIM(J71))) -> Pamela | P71: =IF(K71="","UNKNOWN",PROPER(TRIM(K71))) -> Oneal | Q71: =IF(M71="","UNKNOWN",PROPER(TRIM(M71))) -> Silver | R71: =IFERROR(VLOOKUP(TRIM(L71),State_Mapping!A:B,2,FALSE),"Unknown") -> North Carolina | S71: =IF(C71="","Missing","Valid") -> Valid
A72: ORD114320 | B72: CUST002392 | C72: 2024-03-06 | D72: In-Store | E72: Completed | F72: PayPal | G72: 0 | H72: 0 | I72: 1789.38 | J72: Matthew | K72: Dodson | L72: WI | M72: silver | N72: 2023-08-21 | O72: =IF(J72="","UNKNOWN",PROPER(TRIM(J72))) -> Matthew | P72: =IF(K72="","UNKNOWN",PROPER(TRIM(K72))) -> Dodson | Q72: =IF(M72="","UNKNOWN",PROPER(TRIM(M72))) -> Silver | R72: =IFERROR(VLOOKUP(TRIM(L72),State_Mapping!A:B,2,FALSE),"Unknown") -> Wisconsin | S72: =IF(C72="","Missing","Valid") -> Valid
A73: ORD121937 | B73: CUST004457 | C73: 2024-12-10 | D73: Mobile App | E73: Completed | F73: Gift Card | G73: 0 | H73: 10 | I73: 2780.27 | J73: Mark | K73: Collins | L73: Florida | M73: Bronze | N73: 2024-12-05 | O73: =IF(J73="","UNKNOWN",PROPER(TRIM(J73))) -> Mark | P73: =IF(K73="","UNKNOWN",PROPER(TRIM(K73))) -> Collins | Q73: =IF(M73="","UNKNOWN",PROPER(TRIM(M73))) -> Bronze | R73: =IFERROR(VLOOKUP(TRIM(L73),State_Mapping!A:B,2,FALSE),"Unknown") -> Florida | S73: =IF(C73="","Missing","Valid") -> Valid
A74: ORD105360 | B74: CUST000680 | C74: 2025-02-26 | D74: In-Store | E74: Completed | F74: PayPal | G74: 0 | H74: 20 | I74: 225.79 | J74: Stephanie | K74: Jackson | L74: GA | M74: bronze | N74: 2023-12-05 | O74: =IF(J74="","UNKNOWN",PROPER(TRIM(J74))) -> Stephanie | P74: =IF(K74="","UNKNOWN",PROPER(TRIM(K74))) -> Jackson | Q74: =IF(M74="","UNKNOWN",PROPER(TRIM(M74))) -> Bronze | R74: =IFERROR(VLOOKUP(TRIM(L74),State_Mapping!A:B,2,FALSE),"Unknown") -> Georgia | S74: =IF(C74="","Missing","Valid") -> Valid
A75: ORD124934 | B75: CUST005527 | C75: 2024-07-17 | D75: Mobile App | E75: Completed | F75: Debit Card | G75: 4.99 | H75: 0 | I75: 392.77 | J75: Terrance | K75: Donovan | L75: va | M75: gold | N75: 2024-06-21 | O75: =IF(J75="","UNKNOWN",PROPER(TRIM(J75))) -> Terrance | P75: =IF(K75="","UNKNOWN",PROPER(TRIM(K75))) -> Donovan | Q75: =IF(M75="","UNKNOWN",PROPER(TRIM(M75))) -> Gold | R75: =IFERROR(VLOOKUP(TRIM(L75),State_Mapping!A:B,2,FALSE),"Unknown") -> Virginia | S75: =IF(C75="","Missing","Valid") -> Valid
A76: ORD101585 | B76: CUST006044 | D76: In-Store | E76: Completed | F76: PayPal | G76: 4.99 | H76: 0 | I76: 932.21 | J76: Jonathan | K76: Collins | L76: Pennsylvania | M76: platinum | N76: 2021-11-11 | O76: =IF(J76="","UNKNOWN",PROPER(TRIM(J76))) -> Jonathan | P76: =IF(K76="","UNKNOWN",PROPER(TRIM(K76))) -> Collins | Q76: =IF(M76="","UNKNOWN",PROPER(TRIM(M76))) -> Platinum | R76: =IFERROR(VLOOKUP(TRIM(L76),State_Mapping!A:B,2,FALSE),"Unknown") -> Pennsylvania | S76: =IF(C76="","Missing","Valid") -> Missing
A77: ORD101196 | B77: CUST002069 | C77: 2025-05-11 | D77: Online | E77: Completed | F77: Credit Card | G77: 7.99 | H77: 15 | I77: 2816.23 | J77: Crystal | K77: Wilkinson | L77: ga | M77: BRONZE | N77: 2020-09-24 | O77: =IF(J77="","UNKNOWN",PROPER(TRIM(J77))) -> Crystal | P77: =IF(K77="","UNKNOWN",PROPER(TRIM(K77))) -> Wilkinson | Q77: =IF(M77="","UNKNOWN",PROPER(TRIM(M77))) -> Bronze | R77: =IFERROR(VLOOKUP(TRIM(L77),State_Mapping!A:B,2,FALSE),"Unknown") -> Georgia | S77: =IF(C77="","Missing","Valid") -> Valid
A78: ORD119297 | B78: CUST000059 | C78: 2023-05-08 | D78: In-Store | E78: Completed | F78: Gift Card | G78: 0 | H78: 0 | I78: 470.35 | J78: Joseph | K78: Martinez | L78: NC | M78: bronze | N78: 2021-05-02 | O78: =IF(J78="","UNKNOWN",PROPER(TRIM(J78))) -> Joseph | P78: =IF(K78="","UNKNOWN",PROPER(TRIM(K78))) -> Martinez | Q78: =IF(M78="","UNKNOWN",PROPER(TRIM(M78))) -> Bronze | R78: =IFERROR(VLOOKUP(TRIM(L78),State_Mapping!A:B,2,FALSE),"Unknown") -> North Carolina | S78: =IF(C78="","Missing","Valid") -> Valid
A79: ORD112147 | B79: CUST000033 | C79: 2025-04-02 | D79: Mobile App | E79: Completed | F79: Credit Card | G79: 0 | H79: 0 | I79: 994.12 | J79: Ashley | K79: Barnett | L79: PA | M79: silver | N79: 2023-07-20 | O79: =IF(J79="","UNKNOWN",PROPER(TRIM(J79))) -> Ashley | P79: =IF(K79="","UNKNOWN",PROPER(TRIM(K79))) -> Barnett | Q79: =IF(M79="","UNKNOWN",PROPER(TRIM(M79))) -> Silver | R79: =IFERROR(VLOOKUP(TRIM(L79),State_Mapping!A:B,2,FALSE),"Unknown") -> Pennsylvania | S79: =IF(C79="","Missing","Valid") -> Valid
A80: ORD126366 | B80: CUST004904 | C80: 2024-06-04 | D80: Online | E80: Returned | F80: Debit Card | G80: 4.99 | H80: 0 | I80: 1079.59 | J80: Robert | K80: Allen | L80: VA | M80: SILVER | N80: 2022-07-14
A81: ORD124737 | B81: CUST000122 | C81: 2023-10-30 | D81: In-Store | E81: Completed | F81: Gift Card | G81: 4.99 | H81: 0 | I81: 1876.46 | J81: Christopher | K81: Bruce | L81: IL | M81: Bronze | N81: 2022-08-08 | O81: =IF(J81="","UNKNOWN",PROPER(TRIM(J81))) -> Christopher | P81: =IF(K81="","UNKNOWN",PROPER(TRIM(K81))) -> Bruce | Q81: =IF(M81="","UNKNOWN",PROPER(TRIM(M81))) -> Bronze | R81: =IFERROR(VLOOKUP(TRIM(L81),State_Mapping!A:B,2,FALSE),"Unknown") -> Illinois | S81: =IF(C81="","Missing","Valid") -> Valid
A82: ORD125909 | B82: CUST003077 | C82: 2025-12-29 | D82: Mobile App | E82: Completed | F82: Gift Card | G82: 7.99 | H82: 0 | I82: 1131.9 | J82: Jesse | K82: Drake | L82: md | M82: BRONZE | N82: 2025-01-02 | O82: =IF(J82="","UNKNOWN",PROPER(TRIM(J82))) -> Jesse | P82: =IF(K82="","UNKNOWN",PROPER(TRIM(K82))) -> Drake | Q82: =IF(M82="","UNKNOWN",PROPER(TRIM(M82))) -> Bronze | R82: =IFERROR(VLOOKUP(TRIM(L82),State_Mapping!A:B,2,FALSE),"Unknown") -> Massachusetts | S82: =IF(C82="","Missing","Valid") -> Valid
A83: ORD114677 | B83: CUST005677 | C83: 2026-02-09 | D83: Online | E83: Completed | F83: Debit Card | G83: 5.99 | H83: 0 | I83: 2524.15 | J83: Tara | K83: Jenkins | L83: OH | M83: Bronze | N83: 2023-07-20 | O83: =IF(J83="","UNKNOWN",PROPER(TRIM(J83))) -> Tara | P83: =IF(K83="","UNKNOWN",PROPER(TRIM(K83))) -> Jenkins | Q83: =IF(M83="","UNKNOWN",PROPER(TRIM(M83))) -> Bronze | R83: =IFERROR(VLOOKUP(TRIM(L83),State_Mapping!A:B,2,FALSE),"Unknown") -> Ohio | S83: =IF(C83="","Missing","Valid") -> Valid
A84: ORD110512 | B84: CUST006072 | C84: 2025-07-26 | D84: In-Store | E84: Completed | F84: Store Credit | G84: 0 | H84: 0 | I84: 3822.57 | J84: Tracy | K84: Haley | L84: ARIZONA | M84: bronze | N84: 2025-07-26 | O84: =IF(J84="","UNKNOWN",PROPER(TRIM(J84))) -> Tracy | P84: =IF(K84="","UNKNOWN",PROPER(TRIM(K84))) -> Haley | Q84: =IF(M84="","UNKNOWN",PROPER(TRIM(M84))) -> Bronze | R84: =IFERROR(VLOOKUP(TRIM(L84),State_Mapping!A:B,2,FALSE),"Unknown") -> Arizona | S84: =IF(C84="","Missing","Valid") -> Valid
A85: ORD117570 | B85: CUST004321 | C85: 2023-02-01 | D85: In-Store | E85: Completed | F85: Gift Card | G85: 7.99 | H85: 0 | I85: 984.33 | J85: Timothy | K85: Garcia | L85: NY | M85: bronze | N85: 2020-09-11 | O85: =IF(J85="","UNKNOWN",PROPER(TRIM(J85))) -> Timothy | P85: =IF(K85="","UNKNOWN",PROPER(TRIM(K85))) -> Garcia | Q85: =IF(M85="","UNKNOWN",PROPER(TRIM(M85))) -> Bronze | R85: =IFERROR(VLOOKUP(TRIM(L85),State_Mapping!A:B,2,FALSE),"Unknown") -> New York | S85: =IF(C85="","Missing","Valid") -> Valid
A86: ORD106915 | B86: CUST001841 | C86: 2024-05-20 | D86: In-Store | E86: Cancelled | F86: Credit Card | G86: 0 | H86: 0 | I86: 2786.87 | J86: Peter | K86: Phillips | L86: OH | M86: Bronze | N86: 2024-02-07
A87: ORD120520 | B87: CUST003431 | C87: 2024-10-01 | D87: Mobile App | E87: Completed | F87: PayPal | G87: 7.99 | H87: 5 | I87: 740.23 | J87: Yvonne | K87: Short | L87: AZ | M87: Bronze | N87: 2024-08-16 | O87: =IF(J87="","UNKNOWN",PROPER(TRIM(J87))) -> Yvonne | P87: =IF(K87="","UNKNOWN",PROPER(TRIM(K87))) -> Short | Q87: =IF(M87="","UNKNOWN",PROPER(TRIM(M87))) -> Bronze | R87: =IFERROR(VLOOKUP(TRIM(L87),State_Mapping!A:B,2,FALSE),"Unknown") -> Arizona | S87: =IF(C87="","Missing","Valid") -> Valid
A88: ORD113169 | B88: CUST001610 | D88: Mobile App | E88: Completed | F88: Store Credit | G88: 12.99 | H88: 0 | I88: 2780.86 | J88: Manuel | K88: Brandt | L88: NY | M88: silver | N88: 2024-09-22 | O88: =IF(J88="","UNKNOWN",PROPER(TRIM(J88))) -> Manuel | P88: =IF(K88="","UNKNOWN",PROPER(TRIM(K88))) -> Brandt | Q88: =IF(M88="","UNKNOWN",PROPER(TRIM(M88))) -> Silver | R88: =IFERROR(VLOOKUP(TRIM(L88),State_Mapping!A:B,2,FALSE),"Unknown") -> New York | S88: =IF(C88="","Missing","Valid") -> Missing
A89: ORD101552 | B89: CUST005452 | C89: 2024-08-01 | D89: In-Store | E89: Returned | F89: PayPal | G89: 12.99 | H89: 5 | I89: 6972.53 | J89: Emily | K89: Freeman | L89: mo | M89: bronze | N89: 2023-02-19
A90: ORD122358 | B90: CUST000020 | C90: 2025-06-10 | D90: In-Store | E90: Completed | F90: PayPal | G90: 5.99 | H90: 5 | I90: 928.98 | J90: Monica | K90: Garrison | L90: GA | M90: Silver | N90: 2025-06-05 | O90: =IF(J90="","UNKNOWN",PROPER(TRIM(J90))) -> Monica | P90: =IF(K90="","UNKNOWN",PROPER(TRIM(K90))) -> Garrison | Q90: =IF(M90="","UNKNOWN",PROPER(TRIM(M90))) -> Silver | R90: =IFERROR(VLOOKUP(TRIM(L90),State_Mapping!A:B,2,FALSE),"Unknown") -> Georgia | S90: =IF(C90="","Missing","Valid") -> Valid
A91: ORD117828 | B91: CUST003076 | C91: 2025-12-17 | D91: Online | E91: Completed | F91: Gift Card | G91: 0 | H91: 0 | I91: 1644.43 | J91: Benjamin | K91: Phillips | L91: IN | M91: BRONZE | N91: 2022-03-11 | O91: =IF(J91="","UNKNOWN",PROPER(TRIM(J91))) -> Benjamin | P91: =IF(K91="","UNKNOWN",PROPER(TRIM(K91))) -> Phillips | Q91: =IF(M91="","UNKNOWN",PROPER(TRIM(M91))) -> Bronze | R91: =IFERROR(VLOOKUP(TRIM(L91),State_Mapping!A:B,2,FALSE),"Unknown") -> Indiana | S91: =IF(C91="","Missing","Valid") -> Valid
A92: ORD109281 | B92: CUST001154 | C92: 2025-03-14 | D92: In-Store | E92: Completed | F92: Store Credit | G92: 7.99 | H92: 0 | I92: 2228.29 | J92: Tracy | K92: Hoffman | L92: Arizona | M92: Gold | N92: 2022-07-21 | O92: =IF(J92="","UNKNOWN",PROPER(TRIM(J92))) -> Tracy | P92: =IF(K92="","UNKNOWN",PROPER(TRIM(K92))) -> Hoffman | Q92: =IF(M92="","UNKNOWN",PROPER(TRIM(M92))) -> Gold | R92: =IFERROR(VLOOKUP(TRIM(L92),State_Mapping!A:B,2,FALSE),"Unknown") -> Arizona | S92: =IF(C92="","Missing","Valid") -> Valid
A93: ORD111335 | B93: CUST004155 | C93: 2022-09-05 | D93: Mobile App | E93: Completed | F93: PayPal | G93: 7.99 | H93: 0 | I93: 3197.45 | J93: Emily | K93: Clark | L93: Missouri | M93: Silver | N93: 2020-11-06 | O93: =IF(J93="","UNKNOWN",PROPER(TRIM(J93))) -> Emily | P93: =IF(K93="","UNKNOWN",PROPER(TRIM(K93))) -> Clark | Q93: =IF(M93="","UNKNOWN",PROPER(TRIM(M93))) -> Silver | R93: =IFERROR(VLOOKUP(TRIM(L93),State_Mapping!A:B,2,FALSE),"Unknown") -> Missouri | S93: =IF(C93="","Missing","Valid") -> Valid
A94: ORD125307 | B94: CUST003733 | C94: 2024-09-25 | D94: In-Store | E94: Completed | F94: Store Credit | G94: 0 | H94: 0 | I94: 2618.68 | J94: Randall | K94: Robinson | L94: MA | M94: GOLD | N94: 2021-07-24 | O94: =IF(J94="","UNKNOWN",PROPER(TRIM(J94))) -> Randall | P94: =IF(K94="","UNKNOWN",PROPER(TRIM(K94))) -> Robinson | Q94: =IF(M94="","UNKNOWN",PROPER(TRIM(M94))) -> Gold | R94: =IFERROR(VLOOKUP(TRIM(L94),State_Mapping!A:B,2,FALSE),"Unknown") -> Maryland | S94: =IF(C94="","Missing","Valid") -> Valid
A95: ORD117581 | B95: CUST004860 | C95: 2026-02-25 | D95: Mobile App | E95: Completed | F95: Debit Card | G95: 0 | H95: 15 | I95: 1959.91 | J95: Charles | K95: Vaughn | L95: Illinois | M95: bronze | N95: 2025-10-25 | O95: =IF(J95="","UNKNOWN",PROPER(TRIM(J95))) -> Charles | P95: =IF(K95="","UNKNOWN",PROPER(TRIM(K95))) -> Vaughn | Q95: =IF(M95="","UNKNOWN",PROPER(TRIM(M95))) -> Bronze | R95: =IFERROR(VLOOKUP(TRIM(L95),State_Mapping!A:B,2,FALSE),"Unknown") -> Illinois | S95: =IF(C95="","Missing","Valid") -> Valid
A96: ORD110821 | B96: CUST001728 | C96: 2024-11-03 | D96: Mobile App | E96: Completed | F96: Debit Card | G96: 7.99 | H96: 0 | I96: 2221.49 | J96: Katherine | K96: Turner | L96: NJ | M96: Silver | N96: 2024-01-20 | O96: =IF(J96="","UNKNOWN",PROPER(TRIM(J96))) -> Katherine | P96: =IF(K96="","UNKNOWN",PROPER(TRIM(K96))) -> Turner | Q96: =IF(M96="","UNKNOWN",PROPER(TRIM(M96))) -> Silver | R96: =IFERROR(VLOOKUP(TRIM(L96),State_Mapping!A:B,2,FALSE),"Unknown") -> New Jersey | S96: =IF(C96="","Missing","Valid") -> Valid
A97: ORD126157 | B97: CUST001402 | C97: 2024-05-29 | D97: In-Store | E97: Completed | F97: Gift Card | G97: 12.99 | H97: 0 | I97: 282.76 | J97: Krista | K97: Castillo | L97: wa | M97: BRONZE | N97: 2022-10-02 | O97: =IF(J97="","UNKNOWN",PROPER(TRIM(J97))) -> Krista | P97: =IF(K97="","UNKNOWN",PROPER(TRIM(K97))) -> Castillo | Q97: =IF(M97="","UNKNOWN",PROPER(TRIM(M97))) -> Bronze | R97: =IFERROR(VLOOKUP(TRIM(L97),State_Mapping!A:B,2,FALSE),"Unknown") -> Washington | S97: =IF(C97="","Missing","Valid") -> Valid
A98: ORD112720 | B98: CUST002930 | C98: 2025-10-12 | D98: Online | E98: Completed | F98: Credit Card | G98: 0 | H98: 0 | I98: 2488.5 | J98: Cindy | K98: Harris | L98: NY | M98: SILVER | N98: 2025-06-11 | O98: =IF(J98="","UNKNOWN",PROPER(TRIM(J98))) -> Cindy | P98: =IF(K98="","UNKNOWN",PROPER(TRIM(K98))) -> Harris | Q98: =IF(M98="","UNKNOWN",PROPER(TRIM(M98))) -> Silver | R98: =IFERROR(VLOOKUP(TRIM(L98),State_Mapping!A:B,2,FALSE),"Unknown") -> New York | S98: =IF(C98="","Missing","Valid") -> Valid
A99: ORD119550 | B99: CUST004613 | C99: 2025-06-01 | D99: Mobile App | E99: Completed | F99: Debit Card | G99: 5.99 | H99: 0 | I99: 2064.19 | J99: Kristen | K99: Hoover | L99: NORTH CAROLINA | M99: bronze | N99: 10/30/2022 | O99: =IF(J99="","UNKNOWN",PROPER(TRIM(J99))) -> Kristen | P99: =IF(K99="","UNKNOWN",PROPER(TRIM(K99))) -> Hoover | Q99: =IF(M99="","UNKNOWN",PROPER(TRIM(M99))) -> Bronze | R99: =IFERROR(VLOOKUP(TRIM(L99),State_Mapping!A:B,2,FALSE),"Unknown") -> North Carolina | S99: =IF(C99="","Missing","Valid") -> Valid
A100: ORD104485 | B100: CUST005794 | C100: 2022-05-20 | D100: Mobile App | E100: Completed | F100: Credit Card | G100: 4.99 | H100: 0 | I100: 4674.21 | J100: Haley | K100: King | L100: Pennsylvania | M100: bronze | N100: 2021-05-27 | O100: =IF(J100="","UNKNOWN",PROPER(TRIM(J100))) -> Haley | P100: =IF(K100="","UNKNOWN",PROPER(TRIM(K100))) -> King | Q100: =IF(M100="","UNKNOWN",PROPER(TRIM(M100))) -> Bronze | R100: =IFERROR(VLOOKUP(TRIM(L100),State_Mapping!A:B,2,FALSE),"Unknown") -> Pennsylvania | S100: =IF(C100="","Missing","Valid") -> Valid
A101: ORD127467 | B101: CUST004404 | C101: 2023-05-13 | D101: Online | E101: Completed | F101: Gift Card | G101: 12.99 | H101: 0 | I101: 1626.76 | J101: Vanessa | K101: Bailey | L101: Georgia | M101: bronze | N101: 2021-03-19 | O101: =IF(J101="","UNKNOWN",PROPER(TRIM(J101))) -> Vanessa | P101: =IF(K101="","UNKNOWN",PROPER(TRIM(K101))) -> Bailey | Q101: =IF(M101="","UNKNOWN",PROPER(TRIM(M101))) -> Bronze | R101: =IFERROR(VLOOKUP(TRIM(L101),State_Mapping!A:B,2,FALSE),"Unknown") -> Georgia | S101: =IF(C101="","Missing","Valid") -> Valid
... A105: ORD114939 | B105: CUST004823 | C105: 2024-11-12 | D105: Online | E105: Completed | F105: Debit Card | G105: 5.99 | H105: 5 | I105: 1328.58 | J105: Kelly | K105: Alvarado | L105: MO | M105: Gold | N105: 2024-11-09 | O105: =IF(J105="","UNKNOWN",PROPER(TRIM(J105))) -> Kelly | P105: =IF(K105="","UNKNOWN",PROPER(TRIM(K105))) -> Alvarado | Q105: =IF(M105="","UNKNOWN",PROPER(TRIM(M105))) -> Gold | R105: =IFERROR(VLOOKUP(TRIM(L105),State_Mapping!A:B,2,FALSE),"Unknown") -> Missouri | S105: =IF(C105="","Missing","Valid") -> Valid
A106: ORD111919 | B106: CUST003803 | C106: 2025-05-26 | D106: Online | E106: Returned | F106: Credit Card | G106: 0 | H106: 0 | I106: 1651.81 | J106: Catherine | K106: Meyer | L106: OH | M106: BRONZE | N106: 2022-07-10
A107: ORD121333 | B107: CUST004984 | C107: 2024-01-22 | D107: In-Store | E107: Completed | F107: Credit Card | G107: 4.99 | H107: 0 | I107: 517.43 | J107: Gregory | K107: Martin | L107: IL | M107: bronze | N107: 2021-07-08 | O107: =IF(J107="","UNKNOWN",PROPER(TRIM(J107))) -> Gregory | P107: =IF(K107="","UNKNOWN",PROPER(TRIM(K107))) -> Martin | Q107: =IF(M107="","UNKNOWN",PROPER(TRIM(M107))) -> Bronze | R107: =IFERROR(VLOOKUP(TRIM(L107),State_Mapping!A:B,2,FALSE),"Unknown") -> Illinois | S107: =IF(C107="","Missing","Valid") -> Valid
A108: ORD107563 | B108: CUST002326 | C108: 2023-08-05 | D108: Online | E108: Completed | F108: Debit Card | G108: 0 | H108: 0 | I108: 55.57 | J108: Richard | K108: Johnson | L108: MD | M108: silver | N108: 2023-03-07 | O108: =IF(J108="","UNKNOWN",PROPER(TRIM(J108))) -> Richard | P108: =IF(K108="","UNKNOWN",PROPER(TRIM(K108))) -> Johnson | Q108: =IF(M108="","UNKNOWN",PROPER(TRIM(M108))) -> Silver | R108: =IFERROR(VLOOKUP(TRIM(L108),State_Mapping!A:B,2,FALSE),"Unknown") -> Massachusetts | S108: =IF(C108="","Missing","Valid") -> Valid
A109: ORD122105 | B109: CUST004670 | C109: 2025-09-02 | D109: Online | E109: Pending | F109: PayPal | G109: 4.99 | H109: 0 | I109: 2209.79 | J109: Kimberly | K109: Cervantes | L109: OH | M109: GOLD | N109: 2025-08-28
A110: ORD128131 | B110: CUST005526 | C110: 2025-08-09 | D110: Mobile App | E110: Completed | F110: Gift Card | G110: 0 | H110: 0 | I110: 2088.12 | J110: Vanessa | K110: Shepard | L110: WA | M110: bronze | N110: 2025-07-11 | O110: =IF(J110="","UNKNOWN",PROPER(TRIM(J110))) -> Vanessa | P110: =IF(K110="","UNKNOWN",PROPER(TRIM(K110))) -> Shepard | Q110: =IF(M110="","UNKNOWN",PROPER(TRIM(M110))) -> Bronze | R110: =IFERROR(VLOOKUP(TRIM(L110),State_Mapping!A:B,2,FALSE),"Unknown") -> Washington | S110: =IF(C110="","Missing","Valid") -> Valid
A111: ORD122679 | B111: CUST005838 | C111: 2025-05-27 | D111: Online | E111: Cancelled | F111: Store Credit | G111: 12.99 | H111: 10 | I111: 2375.31 | J111: Phillip | K111: Clay | L111: NY | M111: SILVER | N111: 09/15/2025
A112: ORD121542 | B112: CUST001046 | C112: 2026-06-09 | D112: Online | E112: completed | F112: Gift Card | G112: 0 | H112: 15 | I112: 1454.88 | J112: James | K112: Moreno | L112: NC | M112: Bronze | N112: 2025-10-04 | O112: =IF(J112="","UNKNOWN",PROPER(TRIM(J112))) -> James | P112: =IF(K112="","UNKNOWN",PROPER(TRIM(K112))) -> Moreno | Q112: =IF(M112="","UNKNOWN",PROPER(TRIM(M112))) -> Bronze | R112: =IFERROR(VLOOKUP(TRIM(L112),State_Mapping!A:B,2,FALSE),"Unknown") -> North Carolina | S112: =IF(C112="","Missing","Valid") -> Valid
A113: ORD107377 | B113: CUST003256 | C113: 2026-06-26 | D113: Mobile App | E113: Completed | F113: Credit Card | G113: 7.99 | H113: 0 | I113: 1159.11 | J113: Amy | K113: Bright | L113: MA | M113: gold | N113: 2020-12-04 | O113: =IF(J113="","UNKNOWN",PROPER(TRIM(J113))) -> Amy | P113: =IF(K113="","UNKNOWN",PROPER(TRIM(K113))) -> Bright | Q113: =IF(M113="","UNKNOWN",PROPER(TRIM(M113))) -> Gold | R113: =IFERROR(VLOOKUP(TRIM(L113),State_Mapping!A:B,2,FALSE),"Unknown") -> Maryland | S113: =IF(C113="","Missing","Valid") -> Valid
A114: ORD100031 | B114: CUST002090 | C114: 2024-07-04 | D114: In-Store | E114: Completed | F114: Store Credit | G114: 7.99 | H114: 0 | I114: 5321.74 | J114: William | K114: Morales | L114: GA | M114: bronze | N114: 2024-03-01 | O114: =IF(J114="","UNKNOWN",PROPER(TRIM(J114))) -> William | P114: =IF(K114="","UNKNOWN",PROPER(TRIM(K114))) -> Morales | Q114: =IF(M114="","UNKNOWN",PROPER(TRIM(M114))) -> Bronze | R114: =IFERROR(VLOOKUP(TRIM(L114),State_Mapping!A:B,2,FALSE),"Unknown") -> Georgia | S114: =IF(C114="","Missing","Valid") -> Valid
A115: ORD120444 | B115: CUST002512 | C115: 2024-08-02 | D115: Online | E115: Pending | F115: PayPal | G115: 12.99 | H115: 0 | I115: 616.92 | J115: James | K115: Marshall | L115: Pennsylvania | M115: BRONZE | N115: 2024-04-08
A116: ORD123915 | B116: CUST003295 | C116: 2025-02-09 | D116: Online | E116: Completed | F116: Gift Card | G116: 7.99 | H116: 10 | I116: 20.4 | J116: Elizabeth | K116: Spencer | L116: tn | M116: bronze | N116: 2024-10-10 | O116: =IF(J116="","UNKNOWN",PROPER(TRIM(J116))) -> Elizabeth | P116: =IF(K116="","UNKNOWN",PROPER(TRIM(K116))) -> Spencer | Q116: =IF(M116="","UNKNOWN",PROPER(TRIM(M116))) -> Bronze | R116: =IFERROR(VLOOKUP(TRIM(L116),State_Mapping!A:B,2,FALSE),"Unknown") -> Tennessee | S116: =IF(C116="","Missing","Valid") -> Valid
A117: ORD105875 | B117: CUST004213 | C117: 2023-11-30 | D117: Online | E117: Completed | F117: PayPal | G117: 0 | H117: 0 | I117: 1807.25 | J117: Nichole | K117: Smith | L117: Virginia | M117: BRONZE | N117: 2022-12-21 | O117: =IF(J117="","UNKNOWN",PROPER(TRIM(J117))) -> Nichole | P117: =IF(K117="","UNKNOWN",PROPER(TRIM(K117))) -> Smith | Q117: =IF(M117="","UNKNOWN",PROPER(TRIM(M117))) -> Bronze | R117: =IFERROR(VLOOKUP(TRIM(L117),State_Mapping!A:B,2,FALSE),"Unknown") -> Virginia | S117: =IF(C117="","Missing","Valid") -> Valid
A118: ORD105021 | B118: CUST001563 | C118: 2026-03-26 | D118: Mobile App | E118: Completed | F118: Gift Card | G118: 7.99 | H118: 15 | I118: 532.57 | J118: Jennifer | K118: Bird | L118: California | M118: Gold | N118: 2026-03-11 | O118: =IF(J118="","UNKNOWN",PROPER(TRIM(J118))) -> Jennifer | P118: =IF(K118="","UNKNOWN",PROPER(TRIM(K118))) -> Bird | Q118: =IF(M118="","UNKNOWN",PROPER(TRIM(M118))) -> Gold | R118: =IFERROR(VLOOKUP(TRIM(L118),State_Mapping!A:B,2,FALSE),"Unknown") -> California | S118: =IF(C118="","Missing","Valid") -> Valid
...

Sheet OrderLines_Clean
A1: order_item_id | B1: order_id | C1: product_id | D1: quantity | E1: unit_price_at_purchase | F1: product_name | G1: category | H1: sub_category | I1: brand | J1: customer_id | K1: order_date | L1: channel | M1: order_status | N1: order_status_clean | O1: unit_price_status | P1: sub_category_clean | Q1: order_date_status
A2: OI502661 | B2: ORD124764 | C2: PROD1007 | D2: 1 | E2: 119.59 | F2: Meridian Basics Wellness X | G2: Beauty & Personal Care | H2: Wellness | I2: Meridian Basics | J2: CUST002442 | K2: 2024-01-03 | L2: Online | M2: Completed | N2: =IF(M2="","Unknown",PROPER(TRIM(M2))) -> Completed | O2: =IF(E2="","Missing","Valid") -> Valid | P2: =IF(H2="","Unknown",PROPER(TRIM(H2))) -> Wellness | Q2: =IF(K2="","Missing","Valid") -> Valid
A3: OI504251 | B3: ORD123647 | C3: PROD1066 | D3: 1 | E3: 92.95 | F3: Northfield Fragrance Max | G3: Beauty & Personal Care | H3: Fragrance | I3: Northfield | J3: CUST003540 | K3: 2025-04-09 | L3: Mobile App | M3: Completed | N3: =IF(M3="","Unknown",PROPER(TRIM(M3))) -> Completed | O3: =IF(E3="","Missing","Valid") -> Valid | P3: =IF(H3="","Unknown",PROPER(TRIM(H3))) -> Fragrance | Q3: =IF(K3="","Missing","Valid") -> Valid
A4: OI563095 | B4: ORD120357 | C4: PROD1033 | D4: 3 | E4: 147.37 | F4: Crestline Wellness Classic | G4: Beauty & Personal Care | H4: Wellness | I4: Crestline | J4: CUST003336 | K4: 2026-01-09 | L4: Online | M4: Completed | N4: =IF(M4="","Unknown",PROPER(TRIM(M4))) -> Completed | O4: =IF(E4="","Missing","Valid") -> Valid | P4: =IF(H4="","Unknown",PROPER(TRIM(H4))) -> Wellness | Q4: =IF(K4="","Missing","Valid") -> Valid
A5: OI508966 | B5: ORD109049 | C5: PROD1211 | D5: 1 | E5: 79.19 | F5: Amberly Bedding | G5: Home & Kitchen | H5: Bedding | I5: Amberly | J5: CUST004023 | K5: 2026-04-04 | L5: In-Store | M5: Completed | N5: =IF(M5="","Unknown",PROPER(TRIM(M5))) -> Completed | O5: =IF(E5="","Missing","Valid") -> Valid | P5: =IF(H5="","Unknown",PROPER(TRIM(H5))) -> Bedding | Q5: =IF(K5="","Missing","Valid") -> Valid
A6: OI533946 | B6: ORD127684 | C6: PROD1152 | D6: 3 | E6: 792.04 | F6: Vertex Smartphone Lite | G6: Electronics | H6: Smartphones | I6: Vertex | J6: CUST001077 | K6: 2025-03-21 | L6: Online | M6: Completed | N6: =IF(M6="","Unknown",PROPER(TRIM(M6))) -> Completed | O6: =IF(E6="","Missing","Valid") -> Valid | P6: =IF(H6="","Unknown",PROPER(TRIM(H6))) -> Smartphones | Q6: =IF(K6="","Missing","Valid") -> Valid
A7: OI540748 | B7: ORD121329 | C7: PROD1163 | D7: 1 | E7: 471.74 | F7: Pinecrest Small Appliances Essential | G7: Home & Kitchen | H7: Small Appliances | I7: Pinecrest | J7: CUST000441 | K7: 2025-12-06 | L7: Mobile App | M7: Completed | N7: =IF(M7="","Unknown",PROPER(TRIM(M7))) -> Completed | O7: =IF(E7="","Missing","Valid") -> Valid | P7: =IF(H7="","Unknown",PROPER(TRIM(H7))) -> Small Appliances | Q7: =IF(K7="","Missing","Valid") -> Valid
A8: OI524525 | B8: ORD104018 | C8: PROD1122 | D8: 3 | E8: 26.31 | F8: Solstice Headphones Essential | G8: Electronics | H8: Headphones | I8: Solstice | J8: CUST001843 | K8: 2024-06-27 | L8: Mobile App | M8: Cancelled | N8: =IF(M8="","Unknown",PROPER(TRIM(M8))) -> Cancelled | O8: =IF(E8="","Missing","Valid") -> Valid | P8: =IF(H8="","Unknown",PROPER(TRIM(H8))) -> Headphones | Q8: =IF(K8="","Missing","Valid") -> Valid
A9: OI504130 | B9: ORD118883 | C9: PROD1158 | D9: 2 | E9: 248.11 | F9: Pinecrest Accessories Plus | G9: Apparel | H9: Accessories | I9: Pinecrest | J9: CUST004873 | K9: 2024-02-15 | L9: Online | M9: Returned | N9: =IF(M9="","Unknown",PROPER(TRIM(M9))) -> Returned | O9: =IF(E9="","Missing","Valid") -> Valid | P9: =IF(H9="","Unknown",PROPER(TRIM(H9))) -> Accessories | Q9: =IF(K9="","Missing","Valid") -> Valid
A10: OI568470 | B10: ORD123588 | C10: PROD1106 | D10: 1 | E10: 419.77 | F10: Orion Team Sport Pro | G10: Sports & Outdoors | H10: Team Sports | I10: Orion | J10: CUST003497 | K10: 2023-11-29 | L10: In-Store | M10: Completed | N10: =IF(M10="","Unknown",PROPER(TRIM(M10))) -> Completed | O10: =IF(E10="","Missing","Valid") -> Valid | P10: =IF(H10="","Unknown",PROPER(TRIM(H10))) -> Team Sports | Q10: =IF(K10="","Missing","Valid") -> Valid
A11: OI571275 | B11: ORD101564 | C11: PROD1071 | D11: 1 | E11: 342.46 | F11: Crestline Cycling Plus | G11: Sports & Outdoors | H11: Cycling | I11: Crestline | J11: CUST002458 | K11: 2025-10-26 | L11: Online | M11: Completed | N11: =IF(M11="","Unknown",PROPER(TRIM(M11))) -> Completed | O11: =IF(E11="","Missing","Valid") -> Valid | P11: =IF(H11="","Unknown",PROPER(TRIM(H11))) -> Cycling | Q11: =IF(K11="","Missing","Valid") -> Valid
A12: OI511685 | B12: ORD100958 | C12: PROD1050 | D12: 1 | E12: 36.47 | F12: TrueForm Bedding Essential | G12: Home & Kitchen | H12: Bedding | I12: TrueForm | J12: CUST001439 | K12: 2021-09-12 | L12: Online | M12: Completed | N12: =IF(M12="","Unknown",PROPER(TRIM(M12))) -> Completed | O12: =IF(E12="","Missing","Valid") -> Valid | P12: =IF(H12="","Unknown",PROPER(TRIM(H12))) -> Bedding | Q12: =IF(K12="","Missing","Valid") -> Valid
A13: OI520686 | B13: ORD121250 | C13: PROD1011 | D13: 2 | E13: 215.43 | F13: Solstice Small Appliances Lite | G13: Home & Kitchen | H13: Small Appliances | I13: Solstice | J13: CUST002939 | K13: 2025-08-06 | L13: Mobile App | M13: Completed | N13: =IF(M13="","Unknown",PROPER(TRIM(M13))) -> Completed | O13: =IF(E13="","Missing","Valid") -> Valid | P13: =IF(H13="","Unknown",PROPER(TRIM(H13))) -> Small Appliances | Q13: =IF(K13="","Missing","Valid") -> Valid
... A39: OI519957 | B39: ORD113745 | C39: PROD1132 | D39: 1 | E39: 806.53 | F39: Pinecrest Haircare Essential | G39: Beauty & Personal Care | H39: Haircare | I39: Pinecrest | J39: CUST001315 | K39: 2026-06-05 | L39: Online | M39: Completed | N39: =IF(M39="","Unknown",PROPER(TRIM(M39))) -> Completed | O39: =IF(E39="","Missing","Valid") -> Valid | P39: =IF(H39="","Unknown",PROPER(TRIM(H39))) -> Haircare | Q39: =IF(K39="","Missing","Valid") -> Valid
A40: OI529577 | B40: ORD118514 | C40: PROD1109 | D40: 4 | F40: Vertex Decor Max | G40: Home & Kitchen | H40: Decor | I40: Vertex | J40: CUST000743 | K40: 2025-09-03 | L40: In-Store | M40: Completed | N40: =IF(M40="","Unknown",PROPER(TRIM(M40))) -> Completed | O40: =IF(E40="","Missing","Valid") -> Missing | P40: =IF(H40="","Unknown",PROPER(TRIM(H40))) -> Decor | Q40: =IF(K40="","Missing","Valid") -> Valid
A41: OI554265 | B41: ORD114522 | C41: PROD1140 | D41: 3 | E41: 629.46 | F41: TrueForm Furniture Classic | G41: Home & Kitchen | H41: Furniture | I41: TrueForm | J41: CUST003690 | K41: 2025-11-20 | L41: In-Store | M41: Completed | N41: =IF(M41="","Unknown",PROPER(TRIM(M41))) -> Completed | O41: =IF(E41="","Missing","Valid") -> Valid | P41: =IF(H41="","Unknown",PROPER(TRIM(H41))) -> Furniture | Q41: =IF(K41="","Missing","Valid") -> Valid
A42: OI512680 | B42: ORD105058 | C42: PROD1128 | D42: 1 | E42: 876.84 | F42: Pinecrest Haircare Lite | G42: Beauty & Personal Care | H42: Haircare | I42: Pinecrest | J42: CUST003644 | K42: 2026-01-11 | L42: Online | M42: Completed | N42: =IF(M42="","Unknown",PROPER(TRIM(M42))) -> Completed | O42: =IF(E42="","Missing","Valid") -> Valid | P42: =IF(H42="","Unknown",PROPER(TRIM(H42))) -> Haircare | Q42: =IF(K42="","Missing","Valid") -> Valid
A43: OI528901 | B43: ORD122252 | C43: PROD1186 | D43: 2 | E43: 91.47 | F43: Lumen Smart Home | G43: Electronics | H43: Smart Home | I43: Lumen | J43: CUST005202 | K43: 2025-07-25 | L43: Online | M43: Returned | N43: =IF(M43="","Unknown",PROPER(TRIM(M43))) -> Returned | O43: =IF(E43="","Missing","Valid") -> Valid | P43: =IF(H43="","Unknown",PROPER(TRIM(H43))) -> Smart Home | Q43: =IF(K43="","Missing","Valid") -> Valid
A44: OI549605 | B44: ORD112541 | C44: PROD1035 | D44: 1 | E44: 489.75 | F44: Meridian Basics Women's Clothing Pro | G44: Apparel | H44: Women's Clothing | I44: Meridian Basics | J44: CUST005791 | K44: 2026-03-10 | L44: Online | M44: Completed | N44: =IF(M44="","Unknown",PROPER(TRIM(M44))) -> Completed | O44: =IF(E44="","Missing","Valid") -> Valid | P44: =IF(H44="","Unknown",PROPER(TRIM(H44))) -> Women'S Clothing | Q44: =IF(K44="","Missing","Valid") -> Valid
A45: OI528722 | B45: ORD108696 | C45: PROD1187 | D45: 1 | E45: 57.19 | F45: Meridian Basics Fitness Equipment Classic | G45: Sports & Outdoors | H45: Fitness Equipment | I45: Meridian Basics | J45: CUST005743 | K45: 2026-04-16 | L45: Mobile App | M45: COMPLETED | N45: =IF(M45="","Unknown",PROPER(TRIM(M45))) -> Completed | O45: =IF(E45="","Missing","Valid") -> Valid | P45: =IF(H45="","Unknown",PROPER(TRIM(H45))) -> Fitness Equipment | Q45: =IF(K45="","Missing","Valid") -> Valid
A46: OI569949 | B46: ORD126210 | C46: PROD1133 | D46: 1 | E46: 657.83 | F46: Meridian Basics Smart Home Essential | G46: Electronics | H46: Smart Home | I46: Meridian Basics | J46: CUST000126 | K46: 2024-03-23 | L46: Mobile App | M46: Completed | N46: =IF(M46="","Unknown",PROPER(TRIM(M46))) -> Completed | O46: =IF(E46="","Missing","Valid") -> Valid | P46: =IF(H46="","Unknown",PROPER(TRIM(H46))) -> Smart Home | Q46: =IF(K46="","Missing","Valid") -> Valid
A47: OI559224 | B47: ORD103817 | C47: PROD1095 | D47: 1 | E47: 106.61 | F47: Sabre Cycling X | G47: Sports & Outdoors | H47: Cycling | I47: Sabre | J47: CUST004084 | K47: 2023-04-21 | L47: Mobile App | M47: Completed | N47: =IF(M47="","Unknown",PROPER(TRIM(M47))) -> Completed | O47: =IF(E47="","Missing","Valid") -> Valid | P47: =IF(H47="","Unknown",PROPER(TRIM(H47))) -> Cycling | Q47: =IF(K47="","Missing","Valid") -> Valid
A48: OI519731 | B48: ORD120516 | C48: PROD1128 | D48: 2 | E48: 869.4 | F48: Pinecrest Haircare Lite | G48: Beauty & Personal Care | H48: Haircare | I48: Pinecrest | J48: CUST000457 | K48: 2026-06-03 | L48: Mobile App | M48: Completed | N48: =IF(M48="","Unknown",PROPER(TRIM(M48))) -> Completed | O48: =IF(E48="","Missing","Valid") -> Valid | P48: =IF(H48="","Unknown",PROPER(TRIM(H48))) -> Haircare | Q48: =IF(K48="","Missing","Valid") -> Valid
A49: OI554521 | B49: ORD115310 | C49: PROD1015 | D49: 1 | E49: 379.13 | F49: Lumen Cookware Lite | G49: Home & Kitchen | H49: Cookware | I49: Lumen | J49: CUST002357 | K49: 2026-01-08 | L49: Online | M49: Cancelled | N49: =IF(M49="","Unknown",PROPER(TRIM(M49))) -> Cancelled | O49: =IF(E49="","Missing","Valid") -> Valid | P49: =IF(H49="","Unknown",PROPER(TRIM(H49))) -> Cookware | Q49: =IF(K49="","Missing","Valid") -> Valid
A50: OI511425 | B50: ORD116255 | C50: PROD1165 | D50: 1 | E50: 348.8 | F50: Solstice Smartphones Plus | G50: Electronics | H50: Smartphones | I50: Solstice | J50: CUST000082 | K50: 2026-04-08 | L50: Online | M50: Completed | N50: =IF(M50="","Unknown",PROPER(TRIM(M50))) -> Completed | O50: =IF(E50="","Missing","Valid") -> Valid | P50: =IF(H50="","Unknown",PROPER(TRIM(H50))) -> Smartphones | Q50: =IF(K50="","Missing","Valid") -> Valid
A51: OI556807 | B51: ORD115207 | C51: PROD1209 | D51: 1 | E51: 654.81 | F51: Northfield Women's Clothing Lite | G51: Apparel | H51: Women's Clothing | I51: Northfield | J51: CUST001879 | K51: 2024-09-22 | L51: In-Store | M51: completed | N51: =IF(M51="","Unknown",PROPER(TRIM(M51))) -> Completed | O51: =IF(E51="","Missing","Valid") -> Valid | P51: =IF(H51="","Unknown",PROPER(TRIM(H51))) -> Women'S Clothing | Q51: =IF(K51="","Missing","Valid") -> Valid
A52: OI506530 | B52: ORD119893 | C52: PROD1077 | D52: 1 | E52: 646.09 | F52: TrueForm Women's Clothing Max | G52: Apparel | H52: Women's Clothing | I52: TrueForm | J52: CUST005716 | K52: 2026-01-19 | L52: Online | M52: Pending | N52: =IF(M52="","Unknown",PROPER(TRIM(M52))) -> Pending | O52: =IF(E52="","Missing","Valid") -> Valid | P52: =IF(H52="","Unknown",PROPER(TRIM(H52))) -> Women'S Clothing | Q52: =IF(K52="","Missing","Valid") -> Valid
... A55: OI559647 | B55: ORD115661 | C55: PROD1094 | D55: 2 | E55: 343.71 | F55: Lumen Women's Clothing Classic | G55: Apparel | H55: Women's Clothing | I55: Lumen | J55: CUST004054 | K55: 2025-08-06 | L55: In-Store | M55: Completed | N55: =IF(M55="","Unknown",PROPER(TRIM(M55))) -> Completed | O55: =IF(E55="","Missing","Valid") -> Valid | P55: =IF(H55="","Unknown",PROPER(TRIM(H55))) -> Women'S Clothing | Q55: =IF(K55="","Missing","Valid") -> Valid
A56: OI527662 | B56: ORD121895 | C56: PROD1012 | D56: 2 | F56: Northfield Cycling Lite | G56: Sports & Outdoors | H56: Cycling | I56: Northfield | J56: CUST000670 | K56: 2025-07-30 | L56: Mobile App | M56: Completed | N56: =IF(M56="","Unknown",PROPER(TRIM(M56))) -> Completed | O56: =IF(E56="","Missing","Valid") -> Missing | P56: =IF(H56="","Unknown",PROPER(TRIM(H56))) -> Cycling | Q56: =IF(K56="","Missing","Valid") -> Valid
A57: OI542769 | B57: ORD124235 | C57: PROD1097 | D57: 1 | E57: 251.04 | F57: BrightPath Accessories Plus | G57: Apparel | H57: Accessories | I57: BrightPath | J57: CUST003734 | K57: 2025-08-21 | L57: Mobile App | M57: Completed | N57: =IF(M57="","Unknown",PROPER(TRIM(M57))) -> Completed | O57: =IF(E57="","Missing","Valid") -> Valid | P57: =IF(H57="","Unknown",PROPER(TRIM(H57))) -> Accessories | Q57: =IF(K57="","Missing","Valid") -> Valid
A58: OI505245 | B58: ORD109973 | C58: PROD1126 | D58: 1 | E58: 600.34 | F58: Orion Laptops Essential | G58: Electronics | H58: Laptops | I58: Orion | J58: CUST002084 | K58: 2025-10-10 | L58: Mobile App | M58: Completed | N58: =IF(M58="","Unknown",PROPER(TRIM(M58))) -> Completed | O58: =IF(E58="","Missing","Valid") -> Valid | P58: =IF(H58="","Unknown",PROPER(TRIM(H58))) -> Laptops | Q58: =IF(K58="","Missing","Valid") -> Valid
A59: OI547743 | B59: ORD101716 | C59: PROD1045 | D59: 1 | E59: 116.65 | F59: Sabre Furniture | G59: Home & Kitchen | H59: Furniture | I59: Sabre | J59: CUST003035 | K59: 2026-03-30 | L59: In-Store | M59: Completed | N59: =IF(M59="","Unknown",PROPER(TRIM(M59))) -> Completed | O59: =IF(E59="","Missing","Valid") -> Valid | P59: =IF(H59="","Unknown",PROPER(TRIM(H59))) -> Furniture | Q59: =IF(K59="","Missing","Valid") -> Valid
A60: OI536586 | B60: ORD104480 | C60: PROD1174 | D60: 1 | E60: 331.83 | F60: TrueForm Tablet | G60: Electronics | H60: Tablets | I60: TrueForm | J60: CUST001871 | K60: 2024-06-11 | L60: In-Store | M60: Completed | N60: =IF(M60="","Unknown",PROPER(TRIM(M60))) -> Completed | O60: =IF(E60="","Missing","Valid") -> Valid | P60: =IF(H60="","Unknown",PROPER(TRIM(H60))) -> Tablets | Q60: =IF(K60="","Missing","Valid") -> Valid
A61: OI501685 | B61: ORD119580 | C61: PROD1013 | D61: 1 | E61: 166.51 | F61: TrueForm Fragrance | G61: Beauty & Personal Care | H61: Fragrance | I61: TrueForm | J61: CUST003443 | K61: 2025-03-09 | L61: Mobile App | M61: Completed | N61: =IF(M61="","Unknown",PROPER(TRIM(M61))) -> Completed | O61: =IF(E61="","Missing","Valid") -> Valid | P61: =IF(H61="","Unknown",PROPER(TRIM(H61))) -> Fragrance | Q61: =IF(K61="","Missing","Valid") -> Valid
A62: OI504903 | B62: ORD118748 | C62: PROD1150 | D62: 1 | E62: 51.07 | F62: Pinecrest Skincare Classic | G62: Beauty & Personal Care | H62: Skincare | I62: Pinecrest | J62: CUST003723 | K62: 2024-12-10 | L62: Online | M62: Completed | N62: =IF(M62="","Unknown",PROPER(TRIM(M62))) -> Completed | O62: =IF(E62="","Missing","Valid") -> Valid | P62: =IF(H62="","Unknown",PROPER(TRIM(H62))) -> Skincare | Q62: =IF(K62="","Missing","Valid") -> Valid
A63: OI555894 | B63: ORD117781 | C63: PROD1024 | D63: 1 | E63: 335.28 | F63: Pinecrest Skincare Classic | G63: Beauty & Personal Care | H63: Skincare | I63: Pinecrest | J63: CUST003107 | K63: 2025-01-24 | L63: Online | M63: Completed | N63: =IF(M63="","Unknown",PROPER(TRIM(M63))) -> Completed | O63: =IF(E63="","Missing","Valid") -> Valid | P63: =IF(H63="","Unknown",PROPER(TRIM(H63))) -> Skincare | Q63: =IF(K63="","Missing","Valid") -> Valid
A64: OI551522 | B64: ORD107102 | C64: PROD1031 | D64: 1 | E64: 593.48 | F64: Lumen Cookware Essential | G64: Home & Kitchen | H64: Cookware | I64: Lumen | J64: CUST005612 | K64: 2023-10-04 | L64: In-Store | M64: COMPLETED | N64: =IF(M64="","Unknown",PROPER(TRIM(M64))) -> Completed | O64: =IF(E64="","Missing","Valid") -> Valid | P64: =IF(H64="","Unknown",PROPER(TRIM(H64))) -> Cookware | Q64: =IF(K64="","Missing","Valid") -> Valid
A65: OI508042 | B65: ORD123000 | C65: PROD1006 | D65: 3 | E65: 526.81 | F65: Crestline Decor | G65: Home & Kitchen | H65: Decor | I65: Crestline | J65: CUST002434 | K65: 2022-05-08 | L65: In-Store | M65: Completed | N65: =IF(M65="","Unknown",PROPER(TRIM(M65))) -> Completed | O65: =IF(E65="","Missing","Valid") -> Valid | P65: =IF(H65="","Unknown",PROPER(TRIM(H65))) -> Decor | Q65: =IF(K65="","Missing","Valid") -> Valid
A66: OI538826 | B66: ORD103387 | C66: PROD1204 | D66: 1 | E66: 516.67 | F66: Lumen Small Appliance X | G66: Home & Kitchen | H66: Small Appliances | I66: Lumen | J66: CUST004681 | K66: 2025-04-09 | L66: Mobile App | M66: Completed | N66: =IF(M66="","Unknown",PROPER(TRIM(M66))) -> Completed | O66: =IF(E66="","Missing","Valid") -> Valid | P66: =IF(H66="","Unknown",PROPER(TRIM(H66))) -> Small Appliances | Q66: =IF(K66="","Missing","Valid") -> Valid
A67: OI533660 | B67: ORD123574 | C67: PROD1125 | D67: 1 | E67: 221.84 | F67: Northfield Team Sports Pro | G67: Sports & Outdoors | H67: Team Sports | I67: Northfield | J67: CUST005151 | K67: 2026-02-21 | L67: Online | M67: Completed | N67: =IF(M67="","Unknown",PROPER(TRIM(M67))) -> Completed | O67: =IF(E67="","Missing","Valid") -> Valid | P67: =IF(H67="","Unknown",PROPER(TRIM(H67))) -> Team Sports | Q67: =IF(K67="","Missing","Valid") -> Valid
A68: OI566074 | B68: ORD112569 | C68: PROD1124 | D68: 1 | E68: 983.14 | F68: Crestline Smart Home Essential | G68: Electronics | H68: Smart Home | I68: Crestline | J68: CUST001222 | K68: 2024-06-30 | L68: Online | M68: completed | N68: =IF(M68="","Unknown",PROPER(TRIM(M68))) -> Completed | O68: =IF(E68="","Missing","Valid") -> Valid | P68: =IF(H68="","Unknown",PROPER(TRIM(H68))) -> Smart Home | Q68: =IF(K68="","Missing","Valid") -> Valid
A69: OI549349 | B69: ORD107402 | C69: PROD1117 | D69: 1 | E69: 186.88 | F69: Orion Men's Clothing Max | G69: Apparel | I69: Orion | J69: CUST000157 | K69: 2024-05-26 | L69: Online | M69: Completed | N69: =IF(M69="","Unknown",PROPER(TRIM(M69))) -> Completed | O69: =IF(E69="","Missing","Valid") -> Valid | P69: =IF(H69="","Unknown",PROPER(TRIM(H69))) -> Unknown | Q69: =IF(K69="","Missing","Valid") -> Valid
A70: OI527768 | B70: ORD118859 | C70: PROD1128 | D70: 3 | E70: 843.03 | F70: Pinecrest Haircare Lite | G70: Beauty & Personal Care | H70: Haircare | I70: Pinecrest | J70: CUST004189 | K70: 2025-06-24 | L70: Mobile App | M70: Completed | N70: =IF(M70="","Unknown",PROPER(TRIM(M70))) -> Completed | O70: =IF(E70="","Missing","Valid") -> Valid | P70: =IF(H70="","Unknown",PROPER(TRIM(H70))) -> Haircare | Q70: =IF(K70="","Missing","Valid") -> Valid
A71: OI500760 | B71: ORD111271 | C71: PROD1101 | D71: 2 | E71: 171.61 | F71: Pinecrest Camping Lite | G71: Sports & Outdoors | I71: Pinecrest | J71: CUST005473 | K71: 2025-07-11 | L71: Mobile App | M71: Completed | N71: =IF(M71="","Unknown",PROPER(TRIM(M71))) -> Completed | O71: =IF(E71="","Missing","Valid") -> Valid | P71: =IF(H71="","Unknown",PROPER(TRIM(H71))) -> Unknown | Q71: =IF(K71="","Missing","Valid") -> Valid
A72: OI505343 | B72: ORD103483 | C72: PROD1016 | D72: 3 | E72: 79.81 | F72: Orion Fitness Equipment Max | G72: Sports & Outdoors | H72: Fitness Equipment | I72: Orion | J72: CUST000646 | K72: 2025-08-07 | L72: Mobile App | M72: Completed | N72: =IF(M72="","Unknown",PROPER(TRIM(M72))) -> Completed | O72: =IF(E72="","Missing","Valid") -> Valid | P72: =IF(H72="","Unknown",PROPER(TRIM(H72))) -> Fitness Equipment | Q72: =IF(K72="","Missing","Valid") -> Valid
A73: OI541617 | B73: ORD126876 | C73: PROD1033 | D73: 1 | E73: 142.9 | F73: Crestline Wellness Classic | G73: Beauty & Personal Care | H73: Wellness | I73: Crestline | J73: CUST004197 | K73: 2024-09-04 | L73: Mobile App | M73: Completed | N73: =IF(M73="","Unknown",PROPER(TRIM(M73))) -> Completed | O73: =IF(E73="","Missing","Valid") -> Valid | P73: =IF(H73="","Unknown",PROPER(TRIM(H73))) -> Wellness | Q73: =IF(K73="","Missing","Valid") -> Valid
A74: OI542059 | B74: ORD122353 | C74: PROD1100 | D74: 1 | E74: 352.64 | F74: Cadence Cycling Plus | G74: Sports & Outdoors | H74: Cycling | I74: Cadence | J74: CUST002631 | K74: 2024-05-11 | L74: Mobile App | M74: Completed | N74: =IF(M74="","Unknown",PROPER(TRIM(M74))) -> Completed | O74: =IF(E74="","Missing","Valid") -> Valid | P74: =IF(H74="","Unknown",PROPER(TRIM(H74))) -> Cycling | Q74: =IF(K74="","Missing","Valid") -> Valid
A75: OI511154 | B75: ORD125270 | C75: PROD1033 | D75: 2 | E75: 146.37 | F75: Crestline Wellness Classic | G75: Beauty & Personal Care | H75: Wellness | I75: Crestline | J75: CUST004785 | K75: 2025-12-01 | L75: In-Store | M75: Completed | N75: =IF(M75="","Unknown",PROPER(TRIM(M75))) -> Completed | O75: =IF(E75="","Missing","Valid") -> Valid | P75: =IF(H75="","Unknown",PROPER(TRIM(H75))) -> Wellness | Q75: =IF(K75="","Missing","Valid") -> Valid
A76: OI534507 | B76: ORD104776 | C76: PROD1134 | D76: 1 | E76: 251.17 | F76: Meridian Basics Cycling Essential | G76: Sports & Outdoors | H76: Cycling | I76: Meridian Basics | J76: CUST004929 | K76: 2022-06-07 | L76: Online | M76: Completed | N76: =IF(M76="","Unknown",PROPER(TRIM(M76))) -> Completed | O76: =IF(E76="","Missing","Valid") -> Valid | P76: =IF(H76="","Unknown",PROPER(TRIM(H76))) -> Cycling | Q76: =IF(K76="","Missing","Valid") -> Valid
A77: OI507811 | B77: ORD111767 | C77: PROD1176 | D77: 1 | E77: 403.04 | F77: Amberly Fragrance Essential | G77: Beauty & Personal Care | H77: Fragrance | I77: Amberly | J77: CUST001550 | K77: 2025-12-04 | L77: Online | M77: Completed | N77: =IF(M77="","Unknown",PROPER(TRIM(M77))) -> Completed | O77: =IF(E77="","Missing","Valid") -> Valid | P77: =IF(H77="","Unknown",PROPER(TRIM(H77))) -> Fragrance | Q77: =IF(K77="","Missing","Valid") -> Valid
A78: OI572963 | B78: ORD106229 | C78: PROD1157 | D78: 1 | E78: 746.27 | F78: Amberly Team Sports Plus | G78: Sports & Outdoors | H78: Team Sports | I78: Amberly | J78: CUST004476 | K78: 2024-05-23 | L78: Online | M78: Completed | N78: =IF(M78="","Unknown",PROPER(TRIM(M78))) -> Completed | O78: =IF(E78="","Missing","Valid") -> Valid | P78: =IF(H78="","Unknown",PROPER(TRIM(H78))) -> Team Sports | Q78: =IF(K78="","Missing","Valid") -> Valid
A79: OI538844 | B79: ORD106593 | C79: PROD1039 | D79: 1 | E79: 207.84 | F79: Meridian Basics Smartphones X | G79: Electronics | H79: Smartphones | I79: Meridian Basics | J79: CUST005021 | K79: 2026-05-30 | L79: In-Store | M79: completed | N79: =IF(M79="","Unknown",PROPER(TRIM(M79))) -> Completed | O79: =IF(E79="","Missing","Valid") -> Valid | P79: =IF(H79="","Unknown",PROPER(TRIM(H79))) -> Smartphones | Q79: =IF(K79="","Missing","Valid") -> Valid
A80: OI535703 | B80: ORD121548 | C80: PROD1033 | D80: 1 | E80: 147.98 | F80: Crestline Wellness Classic | G80: Beauty & Personal Care | H80: Wellness | I80: Crestline | J80: CUST005884 | K80: 2025-11-14 | L80: Mobile App | M80: Completed | N80: =IF(M80="","Unknown",PROPER(TRIM(M80))) -> Completed | O80: =IF(E80="","Missing","Valid") -> Valid | P80: =IF(H80="","Unknown",PROPER(TRIM(H80))) -> Wellness | Q80: =IF(K80="","Missing","Valid") -> Valid
A81: OI563754 | B81: ORD112704 | C81: PROD1023 | D81: 2 | E81: 260.4 | F81: BrightPath Fragrance Max | G81: Beauty & Personal Care | H81: Fragrance | I81: BrightPath | J81: CUST005444 | K81: 2026-05-18 | L81: Online | M81: Completed | N81: =IF(M81="","Unknown",PROPER(TRIM(M81))) -> Completed | O81: =IF(E81="","Missing","Valid") -> Valid | P81: =IF(H81="","Unknown",PROPER(TRIM(H81))) -> Fragrance | Q81: =IF(K81="","Missing","Valid") -> Valid
A82: OI569048 | B82: ORD115184 | C82: PROD1045 | D82: 2 | E82: 120.1 | F82: Sabre Furniture | G82: Home & Kitchen | H82: Furniture | I82: Sabre | J82: CUST000614 | K82: 2025-10-29 | L82: Online | M82: Completed | N82: =IF(M82="","Unknown",PROPER(TRIM(M82))) -> Completed | O82: =IF(E82="","Missing","Valid") -> Valid | P82: =IF(H82="","Unknown",PROPER(TRIM(H82))) -> Furniture | Q82: =IF(K82="","Missing","Valid") -> Valid
A83: OI534585 | B83: ORD124870 | C83: PROD1193 | D83: 4 | E83: 179.19 | F83: Crestline Wellness | G83: Beauty & Personal Care | H83: Wellness | I83: Crestline | J83: CUST004885 | K83: 2024-09-18 | L83: In-Store | M83: Completed | N83: =IF(M83="","Unknown",PROPER(TRIM(M83))) -> Completed | O83: =IF(E83="","Missing","Valid") -> Valid | P83: =IF(H83="","Unknown",PROPER(TRIM(H83))) -> Wellness | Q83: =IF(K83="","Missing","Valid") -> Valid
... A100: OI526515 | B100: ORD104427 | C100: PROD1029 | D100: 3 | E100: 37.86 | F100: Northfield Fragrance Pro | G100: Beauty & Personal Care | H100: Fragrance | I100: Northfield | J100: CUST000542 | K100: 2021-09-28 | L100: In-Store | M100: Completed | N100: =IF(M100="","Unknown",PROPER(TRIM(M100))) -> Completed | O100: =IF(E100="","Missing","Valid") -> Valid | P100: =IF(H100="","Unknown",PROPER(TRIM(H100))) -> Fragrance | Q100: =IF(K100="","Missing","Valid") -> Valid
A101: OI502019 | B101: ORD111967 | C101: PROD1205 | D101: 2 | E101: 342.07 | F101: Sabre Cameras Classic | G101: Electronics | I101: Sabre | J101: CUST005235 | K101: 2023-11-08 | L101: In-Store | M101: Completed | N101: =IF(M101="","Unknown",PROPER(TRIM(M101))) -> Completed | O101: =IF(E101="","Missing","Valid") -> Valid | P101: =IF(H101="","Unknown",PROPER(TRIM(H101))) -> Unknown | Q101: =IF(K101="","Missing","Valid") -> Valid
A102: OI568329 | B102: ORD103372 | C102: PROD1213 | D102: 1 | E102: 462.49 | F102: Amberly Smartphone X | G102: Electronics | H102: Smartphones | I102: Amberly | J102: CUST003830 | K102: 2025-03-04 | L102: Online | M102: Completed | N102: =IF(M102="","Unknown",PROPER(TRIM(M102))) -> Completed | O102: =IF(E102="","Missing","Valid") -> Valid | P102: =IF(H102="","Unknown",PROPER(TRIM(H102))) -> Smartphones | Q102: =IF(K102="","Missing","Valid") -> Valid
A103: OI569269 | B103: ORD117105 | C103: PROD1058 | D103: 1 | E103: 500.21 | F103: Nova Accessories | G103: Apparel | H103: Accessories | I103: Nova | J103: CUST000956 | K103: 2026-03-13 | L103: Mobile App | M103: Completed | N103: =IF(M103="","Unknown",PROPER(TRIM(M103))) -> Completed | O103: =IF(E103="","Missing","Valid") -> Valid | P103: =IF(H103="","Unknown",PROPER(TRIM(H103))) -> Accessories | Q103: =IF(K103="","Missing","Valid") -> Valid
A104: OI566697 | B104: ORD107454 | C104: PROD1160 | D104: 4 | E104: 505.92 | F104: Amberly Wellness Pro | G104: Beauty & Personal Care | H104: Wellness | I104: Amberly | J104: CUST000209 | K104: 2026-01-03 | L104: Mobile App | M104: Completed | N104: =IF(M104="","Unknown",PROPER(TRIM(M104))) -> Completed | O104: =IF(E104="","Missing","Valid") -> Valid | P104: =IF(H104="","Unknown",PROPER(TRIM(H104))) -> Wellness | Q104: =IF(K104="","Missing","Valid") -> Valid
A105: OI519407 | B105: ORD100470 | C105: PROD1135 | D105: 3 | E105: 812.34 | F105: Everwood Furniture X | G105: Home & Kitchen | H105: Furniture | I105: Everwood | J105: CUST000055 | K105: 2024-04-15 | L105: In-Store | M105: Cancelled | N105: =IF(M105="","Unknown",PROPER(TRIM(M105))) -> Cancelled | O105: =IF(E105="","Missing","Valid") -> Valid | P105: =IF(H105="","Unknown",PROPER(TRIM(H105))) -> Furniture | Q105: =IF(K105="","Missing","Valid") -> Valid
A106: OI554612 | B106: ORD116189 | C106: PROD1144 | D106: 1 | E106: 255.96 | F106: Amberly Camping Pro | G106: Sports & Outdoors | H106: Camping | I106: Amberly | J106: CUST002508 | K106: 2023-04-25 | L106: Online | M106: Completed | N106: =IF(M106="","Unknown",PROPER(TRIM(M106))) -> Completed | O106: =IF(E106="","Missing","Valid") -> Valid | P106: =IF(H106="","Unknown",PROPER(TRIM(H106))) -> Camping | Q106: =IF(K106="","Missing","Valid") -> Valid
A107: OI563495 | B107: ORD118875 | C107: PROD1112 | D107: 2 | E107: 180.02 | F107: Meridian Basics Footwear Pro | G107: Apparel | H107: Footwear | I107: Meridian Basics | J107: CUST001735 | K107: 2026-04-26 | L107: Mobile App | M107: Completed | N107: =IF(M107="","Unknown",PROPER(TRIM(M107))) -> Completed | O107: =IF(E107="","Missing","Valid") -> Valid | P107: =IF(H107="","Unknown",PROPER(TRIM(H107))) -> Footwear | Q107: =IF(K107="","Missing","Valid") -> Valid
A108: OI540202 | B108: ORD115354 | C108: PROD1130 | D108: 1 | E108: 687.75 | F108: Nova Haircare | G108: Beauty & Personal Care | I108: Nova | J108: CUST003010 | K108: 2023-12-09 | L108: Online | M108: Completed | N108: =IF(M108="","Unknown",PROPER(TRIM(M108))) -> Completed | O108: =IF(E108="","Missing","Valid") -> Valid | P108: =IF(H108="","Unknown",PROPER(TRIM(H108))) -> Unknown | Q108: =IF(K108="","Missing","Valid") -> Valid
A109: OI551111 | B109: ORD115610 | C109: PROD1024 | D109: 2 | E109: 331.49 | F109: Pinecrest Skincare Classic | G109: Beauty & Personal Care | H109: Skincare | I109: Pinecrest | J109: CUST001994 | K109: 2026-06-23 | L109: Mobile App | M109: Cancelled | N109: =IF(M109="","Unknown",PROPER(TRIM(M109))) -> Cancelled | O109: =IF(E109="","Missing","Valid") -> Valid | P109: =IF(H109="","Unknown",PROPER(TRIM(H109))) -> Skincare | Q109: =IF(K109="","Missing","Valid") -> Valid
A110: OI526973 | B110: ORD112452 | C110: PROD1139 | D110: 1 | E110: 696.62 | F110: Meridian Basics Men's Clothing | G110: Apparel | H110: Men's Clothing | I110: Meridian Basics | J110: CUST005631 | K110: 2025-06-05 | L110: Mobile App | M110: Completed | N110: =IF(M110="","Unknown",PROPER(TRIM(M110))) -> Completed | O110: =IF(E110="","Missing","Valid") -> Valid | P110: =IF(H110="","Unknown",PROPER(TRIM(H110))) -> Men'S Clothing | Q110: =IF(K110="","Missing","Valid") -> Valid
A111: OI540335 | B111: ORD101864 | C111: PROD1139 | D111: 3 | E111: 681.27 | F111: Meridian Basics Men's Clothing | G111: Apparel | H111: Men's Clothing | I111: Meridian Basics | J111: CUST001442 | K111: 2024-10-20 | L111: Mobile App | M111: Completed | N111: =IF(M111="","Unknown",PROPER(TRIM(M111))) -> Completed | O111: =IF(E111="","Missing","Valid") -> Valid | P111: =IF(H111="","Unknown",PROPER(TRIM(H111))) -> Men'S Clothing | Q111: =IF(K111="","Missing","Valid") -> Valid
A112: OI503651 | B112: ORD110156 | C112: PROD1179 | D112: 1 | E112: 777.84 | F112: Meridian Basics Wellness Lite | G112: Beauty & Personal Care | H112: Wellness | I112: Meridian Basics | J112: CUST004861 | K112: 2025-02-02 | L112: Online | M112: Completed | N112: =IF(M112="","Unknown",PROPER(TRIM(M112))) -> Completed | O112: =IF(E112="","Missing","Valid") -> Valid | P112: =IF(H112="","Unknown",PROPER(TRIM(H112))) -> Wellness | Q112: =IF(K112="","Missing","Valid") -> Valid
A113: OI539173 | B113: ORD106191 | C113: PROD1170 | D113: 1 | E113: 382.01 | F113: Cadence Accessories Max | G113: Apparel | H113: Accessories | I113: Cadence | J113: CUST001345 | K113: 2024-01-24 | L113: Mobile App | M113: Completed | N113: =IF(M113="","Unknown",PROPER(TRIM(M113))) -> Completed | O113: =IF(E113="","Missing","Valid") -> Valid | P113: =IF(H113="","Unknown",PROPER(TRIM(H113))) -> Accessories | Q113: =IF(K113="","Missing","Valid") -> Valid
A114: OI512456 | B114: ORD127601 | C114: PROD1112 | D114: 1 | E114: 176.07 | F114: Meridian Basics Footwear Pro | G114: Apparel | H114: Footwear | I114: Meridian Basics | J114: CUST004007 | K114: 2021-08-02 | L114: Mobile App | M114: Completed | N114: =IF(M114="","Unknown",PROPER(TRIM(M114))) -> Completed | O114: =IF(E114="","Missing","Valid") -> Valid | P114: =IF(H114="","Unknown",PROPER(TRIM(H114))) -> Footwear | Q114: =IF(K114="","Missing","Valid") -> Valid
A115: OI549975 | B115: ORD109599 | C115: PROD1101 | D115: 1 | E115: 177.63 | F115: Pinecrest Camping Lite | G115: Sports & Outdoors | I115: Pinecrest | J115: CUST003157 | K115: 2026-04-03 | L115: In-Store | M115: Completed | N115: =IF(M115="","Unknown",PROPER(TRIM(M115))) -> Completed | O115: =IF(E115="","Missing","Valid") -> Valid | P115: =IF(H115="","Unknown",PROPER(TRIM(H115))) -> Unknown | Q115: =IF(K115="","Missing","Valid") -> Valid
A116: OI566190 | B116: ORD107056 | C116: PROD1209 | D116: 1 | E116: 624.75 | F116: Northfield Women's Clothing Lite | G116: Apparel | H116: Women's Clothing | I116: Northfield | J116: CUST003375 | K116: 2025-04-21 | L116: Mobile App | M116: Completed | N116: =IF(M116="","Unknown",PROPER(TRIM(M116))) -> Completed | O116: =IF(E116="","Missing","Valid") -> Valid | P116: =IF(H116="","Unknown",PROPER(TRIM(H116))) -> Women'S Clothing | Q116: =IF(K116="","Missing","Valid") -> Valid
A117: OI507439 | B117: ORD117261 | C117: PROD1215 | D117: 1 | E117: 143.86 | F117: Northfield Women's Clothing Pro | G117: Apparel | H117: Women's Clothing | I117: Northfield | J117: CUST004341 | K117: 2026-05-01 | L117: Mobile App | M117: Completed | N117: =IF(M117="","Unknown",PROPER(TRIM(M117))) -> Completed | O117: =IF(E117="","Missing","Valid") -> Valid | P117: =IF(H117="","Unknown",PROPER(TRIM(H117))) -> Women'S Clothing | Q117: =IF(K117="","Missing","Valid") -> Valid
A118: OI539074 | B118: ORD126020 | C118: PROD1157 | D118: 1 | E118: 755.77 | F118: Amberly Team Sports Plus | G118: Sports & Outdoors | H118: Team Sports | I118: Amberly | J118: CUST002600 | K118: 2022-10-24 | L118: Online | M118: Completed | N118: =IF(M118="","Unknown",PROPER(TRIM(M118))) -> Completed | O118: =IF(E118="","Missing","Valid") -> Valid | P118: =IF(H118="","Unknown",PROPER(TRIM(H118))) -> Team Sports | Q118: =IF(K118="","Missing","Valid") -> Valid
A119: OI512348 | B119: ORD110500 | C119: PROD1190 | D119: 3 | E119: 118.95 | F119: Amberly Camping Max | G119: Sports & Outdoors | H119: Camping | I119: Amberly | J119: CUST000895 | K119: 2023-08-09 | L119: Mobile App | M119: Completed | N119: =IF(M119="","Unknown",PROPER(TRIM(M119))) -> Completed | O119: =IF(E119="","Missing","Valid") -> Valid | P119: =IF(H119="","Unknown",PROPER(TRIM(H119))) -> Camping | Q119: =IF(K119="","Missing","Valid") -> Valid
A120: OI567024 | B120: ORD114571 | C120: PROD1052 | D120: 1 | E120: 579.57 | F120: Orion Haircare Essential | G120: Beauty & Personal Care | H120: Haircare | I120: Orion | J120: CUST001558 | K120: 2023-06-26 | L120: In-Store | M120: Completed | N120: =IF(M120="","Unknown",PROPER(TRIM(M120))) -> Completed | O120: =IF(E120="","Missing","Valid") -> Valid | P120: =IF(H120="","Unknown",PROPER(TRIM(H120))) -> Haircare | Q120: =IF(K120="","Missing","Valid") -> Valid
A121: OI517144 | B121: ORD103228 | C121: PROD1047 | D121: 1 | E121: 620.69 | F121: Solstice Footwear Classic | G121: Apparel | H121: Footwear | I121: Solstice | J121: CUST003653 | K121: 2025-11-27 | L121: Mobile App | M121: Completed | N121: =IF(M121="","Unknown",PROPER(TRIM(M121))) -> Completed | O121: =IF(E121="","Missing","Valid") -> Valid | P121: =IF(H121="","Unknown",PROPER(TRIM(H121))) -> Footwear | Q121: =IF(K121="","Missing","Valid") -> Valid
A122: OI542245 | B122: ORD107580 | C122: PROD1036 | D122: 1 | E122: 15.48 | F122: Amberly Bedding Max | G122: Home & Kitchen | H122: Bedding | I122: Amberly | J122: CUST000029 | K122: 2023-10-07 | L122: Mobile App | M122: Completed | N122: =IF(M122="","Unknown",PROPER(TRIM(M122))) -> Completed | O122: =IF(E122="","Missing","Valid") -> Valid | P122: =IF(H122="","Unknown",PROPER(TRIM(H122))) -> Bedding | Q122: =IF(K122="","Missing","Valid") -> Valid
A123: OI510783 | B123: ORD124630 | C123: PROD1187 | D123: 1 | E123: 55.21 | F123: Meridian Basics Fitness Equipment Classic | G123: Sports & Outdoors | H123: Fitness Equipment | I123: Meridian Basics | J123: CUST000032 | K123: 2026-03-21 | L123: Online | M123: Completed | N123: =IF(M123="","Unknown",PROPER(TRIM(M123))) -> Completed | O123: =IF(E123="","Missing","Valid") -> Valid | P123: =IF(H123="","Unknown",PROPER(TRIM(H123))) -> Fitness Equipment | Q123: =IF(K123="","Missing","Valid") -> Valid
A124: OI545647 | B124: ORD115968 | C124: PROD1050 | D124: 2 | E124: 35.52 | F124: TrueForm Bedding Essential | G124: Home & Kitchen | H124: Bedding | I124: TrueForm | J124: CUST005946 | K124: 2022-10-20 | L124: In-Store | M124: Pending | N124: =IF(M124="","Unknown",PROPER(TRIM(M124))) -> Pending | O124: =IF(E124="","Missing","Valid") -> Valid | P124: =IF(H124="","Unknown",PROPER(TRIM(H124))) -> Bedding | Q124: =IF(K124="","Missing","Valid") -> Valid
A125: OI540111 | B125: ORD116028 | C125: PROD1109 | D125: 2 | E125: 663.93 | F125: Vertex Decor Max | G125: Home & Kitchen | H125: Decor | I125: Vertex | J125: CUST001160 | K125: 2021-05-25 | L125: Online | M125: Completed | N125: =IF(M125="","Unknown",PROPER(TRIM(M125))) -> Completed | O125: =IF(E125="","Missing","Valid") -> Valid | P125: =IF(H125="","Unknown",PROPER(TRIM(H125))) -> Decor | Q125: =IF(K125="","Missing","Valid") -> Valid
A126: OI504454 | B126: ORD101173 | C126: PROD1059 | D126: 2 | E126: 736.07 | F126: Lumen Team Sports Lite | G126: Sports & Outdoors | H126: Team Sports | I126: Lumen | J126: CUST005871 | K126: 2025-05-27 | L126: In-Store | M126: Completed | N126: =IF(M126="","Unknown",PROPER(TRIM(M126))) -> Completed | O126: =IF(E126="","Missing","Valid") -> Valid | P126: =IF(H126="","Unknown",PROPER(TRIM(H126))) -> Team Sports | Q126: =IF(K126="","Missing","Valid") -> Valid
A127: OI525051 | B127: ORD124960 | C127: PROD1022 | D127: 1 | E127: 242.82 | F127: Sabre Smart Home Max | G127: Electronics | H127: Smart Home | I127: Sabre | J127: CUST000064 | K127: 2025-07-25 | L127: In-Store | M127: Completed | N127: =IF(M127="","Unknown",PROPER(TRIM(M127))) -> Completed | O127: =IF(E127="","Missing","Valid") -> Valid | P127: =IF(H127="","Unknown",PROPER(TRIM(H127))) -> Smart Home | Q127: =IF(K127="","Missing","Valid") -> Valid
... A146: OI500856 | B146: ORD117313 | C146: PROD1099 | D146: 2 | E146: 874.33 | F146: Orion Tablet | G146: Electronics | H146: Tablets | I146: Orion | J146: CUST004532 | K146: 2022-06-30 | L146: In-Store | M146: Completed | N146: =IF(M146="","Unknown",PROPER(TRIM(M146))) -> Completed | O146: =IF(E146="","Missing","Valid") -> Valid | P146: =IF(H146="","Unknown",PROPER(TRIM(H146))) -> Tablets | Q146: =IF(K146="","Missing","Valid") -> Valid
A147: OI526635 | B147: ORD119709 | C147: PROD1162 | D147: 1 | E147: 893.83 | F147: Crestline Smart Home Pro | G147: Electronics | I147: Crestline | J147: CUST000113 | K147: 2024-04-05 | L147: Online | M147: Completed | N147: =IF(M147="","Unknown",PROPER(TRIM(M147))) -> Completed | O147: =IF(E147="","Missing","Valid") -> Valid | P147: =IF(H147="","Unknown",PROPER(TRIM(H147))) -> Unknown | Q147: =IF(K147="","Missing","Valid") -> Valid
A148: OI572197 | B148: ORD117367 | C148: PROD1193 | D148: 3 | E148: 174.9 | F148: Crestline Wellness | G148: Beauty & Personal Care | H148: Wellness | I148: Crestline | J148: CUST000898 | K148: 2024-04-06 | L148: In-Store | M148: Completed | N148: =IF(M148="","Unknown",PROPER(TRIM(M148))) -> Completed | O148: =IF(E148="","Missing","Valid") -> Valid | P148: =IF(H148="","Unknown",PROPER(TRIM(H148))) -> Wellness | Q148: =IF(K148="","Missing","Valid") -> Valid
A149: OI542831 | B149: ORD113234 | C149: PROD1093 | D149: 2 | E149: 694.9 | F149: TrueForm Small Appliances Pro | G149: Home & Kitchen | H149: Small Appliances | I149: TrueForm | J149: CUST001009 | K149: 2021-08-08 | L149: In-Store | M149: Completed | N149: =IF(M149="","Unknown",PROPER(TRIM(M149))) -> Completed | O149: =IF(E149="","Missing","Valid") -> Valid | P149: =IF(H149="","Unknown",PROPER(TRIM(H149))) -> Small Appliances | Q149: =IF(K149="","Missing","Valid") -> Valid
A150: OI518583 | B150: ORD127492 | C150: PROD1067 | D150: 1 | E150: 667.25 | F150: Nova Smart Home Max | G150: Electronics | H150: Smart Home | I150: Nova | J150: CUST003001 | K150: 2024-07-03 | L150: Online | M150: Completed | N150: =IF(M150="","Unknown",PROPER(TRIM(M150))) -> Completed | O150: =IF(E150="","Missing","Valid") -> Valid | P150: =IF(H150="","Unknown",PROPER(TRIM(H150))) -> Smart Home | Q150: =IF(K150="","Missing","Valid") -> Valid
A151: OI529645 | B151: ORD101790 | C151: PROD1006 | D151: 1 | E151: 514.84 | F151: Crestline Decor | G151: Home & Kitchen | H151: Decor | I151: Crestline | J151: CUST004569 | K151: 2026-03-28 | L151: Mobile App | M151: Completed | N151: =IF(M151="","Unknown",PROPER(TRIM(M151))) -> Completed | O151: =IF(E151="","Missing","Valid") -> Valid | P151: =IF(H151="","Unknown",PROPER(TRIM(H151))) -> Decor | Q151: =IF(K151="","Missing","Valid") -> Valid
A152: OI544039 | B152: ORD114806 | C152: PROD1199 | D152: 1 | F152: Orion Smartphones Essential | G152: Electronics | H152: Smartphones | I152: Orion | J152: CUST003490 | K152: 2026-05-15 | L152: Online | M152: Completed | N152: =IF(M152="","Unknown",PROPER(TRIM(M152))) -> Completed | O152: =IF(E152="","Missing","Valid") -> Missing | P152: =IF(H152="","Unknown",PROPER(TRIM(H152))) -> Smartphones | Q152: =IF(K152="","Missing","Valid") -> Valid
A153: OI559113 | B153: ORD113666 | C153: PROD1010 | D153: 4 | E153: 364.69 | F153: Cadence Wellnes X | G153: Beauty & Personal Care | H153: Wellness | I153: Cadence | J153: CUST000802 | K153: 2025-03-03 | L153: Online | M153: Completed | N153: =IF(M153="","Unknown",PROPER(TRIM(M153))) -> Completed | O153: =IF(E153="","Missing","Valid") -> Valid | P153: =IF(H153="","Unknown",PROPER(TRIM(H153))) -> Wellness | Q153: =IF(K153="","Missing","Valid") -> Valid
A154: OI566616 | B154: ORD124629 | C154: PROD1095 | D154: 2 | E154: 103.4 | F154: Sabre Cycling X | G154: Sports & Outdoors | H154: Cycling | I154: Sabre | J154: CUST000032 | K154: 2026-05-18 | L154: In-Store | M154: Completed | N154: =IF(M154="","Unknown",PROPER(TRIM(M154))) -> Completed | O154: =IF(E154="","Missing","Valid") -> Valid | P154: =IF(H154="","Unknown",PROPER(TRIM(H154))) -> Cycling | Q154: =IF(K154="","Missing","Valid") -> Valid
A155: OI557220 | B155: ORD100483 | C155: PROD1047 | D155: 2 | E155: 605.23 | F155: Solstice Footwear Classic | G155: Apparel | H155: Footwear | I155: Solstice | J155: CUST001411 | K155: 2025-04-28 | L155: Mobile App | M155: Completed | N155: =IF(M155="","Unknown",PROPER(TRIM(M155))) -> Completed | O155: =IF(E155="","Missing","Valid") -> Valid | P155: =IF(H155="","Unknown",PROPER(TRIM(H155))) -> Footwear | Q155: =IF(K155="","Missing","Valid") -> Valid
A156: OI563332 | B156: ORD111427 | C156: PROD1216 | D156: 1 | E156: 354.55 | F156: Northfield Women's Clothing Plus | G156: Apparel | H156: Women's Clothing | I156: Northfield | J156: CUST002864 | K156: 2025-11-20 | L156: In-Store | M156: Completed | N156: =IF(M156="","Unknown",PROPER(TRIM(M156))) -> Completed | O156: =IF(E156="","Missing","Valid") -> Valid | P156: =IF(H156="","Unknown",PROPER(TRIM(H156))) -> Women'S Clothing | Q156: =IF(K156="","Missing","Valid") -> Valid
A157: OI543067 | B157: ORD101423 | C157: PROD1219 | D157: 1 | E157: 389.5 | F157: Orion Cycling Max | G157: Sports & Outdoors | H157: Cycling | I157: Orion | J157: CUST005852 | K157: 2023-01-14 | L157: In-Store | M157: Completed | N157: =IF(M157="","Unknown",PROPER(TRIM(M157))) -> Completed | O157: =IF(E157="","Missing","Valid") -> Valid | P157: =IF(H157="","Unknown",PROPER(TRIM(H157))) -> Cycling | Q157: =IF(K157="","Missing","Valid") -> Valid
A158: OI538417 | B158: ORD108341 | C158: PROD1195 | D158: 4 | E158: 755.74 | F158: Meridian Basics Headphones Plus | G158: Electronics | H158: Headphones | I158: Meridian Basics | J158: CUST003785 | K158: 2025-02-26 | L158: In-Store | M158: Completed | N158: =IF(M158="","Unknown",PROPER(TRIM(M158))) -> Completed | O158: =IF(E158="","Missing","Valid") -> Valid | P158: =IF(H158="","Unknown",PROPER(TRIM(H158))) -> Headphones | Q158: =IF(K158="","Missing","Valid") -> Valid
A159: OI510971 | B159: ORD128211 | C159: PROD1031 | D159: 2 | E159: 606.99 | F159: Lumen Cookware Essential | G159: Home & Kitchen | H159: Cookware | I159: Lumen | J159: CUST002299 | K159: 2022-06-18 | L159: Online | M159: Completed | N159: =IF(M159="","Unknown",PROPER(TRIM(M159))) -> Completed | O159: =IF(E159="","Missing","Valid") -> Valid | P159: =IF(H159="","Unknown",PROPER(TRIM(H159))) -> Cookware | Q159: =IF(K159="","Missing","Valid") -> Valid
A160: OI541695 | B160: ORD120658 | C160: PROD1083 | D160: 3 | E160: 202.54 | F160: BrightPath Smart Home Pro | G160: Electronics | H160: Smart Home | I160: BrightPath | J160: CUST002699 | K160: 2026-04-04 | L160: Online | M160: Cancelled | N160: =IF(M160="","Unknown",PROPER(TRIM(M160))) -> Cancelled | O160: =IF(E160="","Missing","Valid") -> Valid | P160: =IF(H160="","Unknown",PROPER(TRIM(H160))) -> Smart Home | Q160: =IF(K160="","Missing","Valid") -> Valid
A161: OI521025 | B161: ORD114585 | C161: PROD1049 | D161: 1 | E161: 19.62 | F161: Vertex Small Appliances X | G161: Home & Kitchen | H161: Small Appliances | I161: Vertex | J161: CUST005432 | K161: 2025-08-04 | L161: In-Store | M161: Completed | N161: =IF(M161="","Unknown",PROPER(TRIM(M161))) -> Completed | O161: =IF(E161="","Missing","Valid") -> Valid | P161: =IF(H161="","Unknown",PROPER(TRIM(H161))) -> Small Appliances | Q161: =IF(K161="","Missing","Valid") -> Valid
...

Sheet State_Mapping
A1: Original | B1: Standardized
A2: Indiana | B2: Indiana
A3: WISCONSIN | B3: Wisconsin
A4: GA | B4: Georgia
A5: PA | B5: Pennsylvania
A6: NY | B6: New York
A7: Wisconsin | B7: Wisconsin
A8: OH | B8: Ohio
A9: Michigan | B9: Michigan
A10: New York | B10: New York
A11: NC | B11: North Carolina
A12: Missouri | B12: Missouri
... A81: INDIANA | B81: Indiana

Sheet Descriptive_Stats
A1: Statistic | B1: Order Value | C1: Shipping Cost
A2: Mean | B2: =AVERAGE(Orders_Clean!I2:I1000) -> 1547.2997 | C2: =AVERAGE(Orders_Clean!G2:G1000) -> 5.2116575
A3: Median | B3: =MEDIAN(Orders_Clean!I2:I1000) -> 1278.85 | C3: =MEDIAN(Orders_Clean!G2:G1000) -> 4.99
A4: Standard Deviation | B4: =STDEV(Orders_Clean!I2:I1000) -> 1178.7747 | C4: =STDEV(Orders_Clean!G2:G1000) -> 4.4820307
A5: Minimum | B5: =MIN(Orders_Clean!I2:I1000) -> 12.1 | C5: =MIN(Orders_Clean!G2:G1000) -> 0
A6: maximum | B6: =MAX(Orders_Clean!I2:I1000) -> 8688.53 | C6: =MAX(Orders_Clean!G2:G1000) -> 12.99

Sheet Pivot_Category_Channel

Sheet Pivot_Revenue_State_Tier

Sheet Data_Quality_Log
A1: DOCUMENT OF DATA-QUALITY ISSUES
A3: Sheet | B3: Column | C3: Issue | D3: Formula | E3: Decision | F3: Justification
A4: Orders | B4: first_name | C4: Extra spaces | D4: TRIM() | E4: Cleaned | F4: Ensures consistency
A5: Orders | B5: order_status | C5: Mixed casing | D5: PROPER(TRIM()) | E5: Standardized | F5: Prevents duplicate categories
A6: Orders | B6: membership_tier | C6: Mixed casing | D6: PROPER(TRIM()) | E6: Standardized | F6: Supports accurate grouping
A7: Orders | B7: state | C7: Abbreviations/full names | D7: VLOOKUP() | E7: Standardized | F7: Prevents duplicate geographic groups
A8: Orders | B8: order_date | C8: Missing values | D8: IF() flag | E8: Flagged | F8: Dates should not be fabricated
A9: OrderLines | B9: unit_price | C9: Missing values | D9: IF() flag | E9: Flagged | F9: Missing ≠ zero
A10: OrderLines | B10: sub_category | C10: Missing values | D10: IF() | E10: Unknown | F10: Avoid guessing categories
A11: OrderLines | B11: order_status | C11: Mixed casing | D11: PROPER(TRIM()) | E11: Standardized | F11: Ensures consistency
